[
  {
    "categoria": "adult / White / male / Rooster",
    "ranking": [
      {
        "posicao": 1,
        "nome": "Samuel Mann",
        "academia": "Renzo Gracie"
      },
      {
        "posicao": 2,
        "nome": "Emil Nguyen",
        "academia": "Tinguinha"
      },
      {
        "posicao": 3,
        "nome": "Jonathon Gaxiola",
        "academia": "Kugtar"
      },
      {
        "posicao": 3,
        "nome": "Michael Azer",
        "academia": "Pedro Soriano"
      }
    ]
  },
  {
    "categoria": "adult / White / male / Light Feather",
    "ranking": [
      {
        "posicao": 1,
        "nome": "Joey Bareng",
        "academia": "Rickson"
      },
      {
        "posicao": 2,
        "nome": "Rene Lopes",
        "academia": "Legion Jiu-jitsu"
      },
      {
        "posicao": 3,
        "nome": "Alexander Condos",
        "academia": "Renzo Gracie"
      },
      {
        "posicao": 3,
        "nome": "Adam Rios",
        "academia": "BJJ Revolution Team"
      }
    ]
  },
  {
    "categoria": "adult / White / male / Feather",
    "ranking": [
      {
        "posicao": 1,
        "nome": "Scott Kawamoto",
        "academia": "BJJ Revolution Team"
      },
      {
        "posicao": 2,
        "nome": "Joseph Park",
        "academia": "BJJ Revolution Team"
      },
      {
        "posicao": 3,
        "nome": "Meath Pedigo",
        "academia": "Vaghi Martial Arts"
      },
      {
        "posicao": 3,
        "nome": "Jeffrey Cummings",
        "academia": "Alliance"
      }
    ]
  },
  {
    "categoria": "adult / White / male / Light",
    "ranking": [
      {
        "posicao": 1,
        "nome": "Michael Straton",
        "academia": "No Limit/ Lotus Club"
      },
      {
        "posicao": 2,
        "nome": "Travis Gmeiner",
        "academia": "Gracie Barra Rohnert Park"
      },
      {
        "posicao": 3,
        "nome": "John Walsh",
        "academia": "Ralph Gracie"
      },
      {
        "posicao": 3,
        "nome": "Dan Lukemart",
        "academia": "Ralph Gracie"
      }
    ]
  },
  {
    "categoria": "adult / White / male / Middle",
    "ranking": [
      {
        "posicao": 1,
        "nome": "Sergio Pena",
        "academia": "Lotus Club"
      },
      {
        "posicao": 2,
        "nome": "Rene Karamantis",
        "academia": "Gracie Barra Panama"
      },
      {
        "posicao": 3,
        "nome": "Jason Romanello",
        "academia": "Rickson"
      },
      {
        "posicao": 3,
        "nome": "Anthony Esguerra",
        "academia": "Groundworks JJ House"
      }
    ]
  },
  {
    "categoria": "adult / White / male / Medium Heavy",
    "ranking": [
      {
        "posicao": 1,
        "nome": "Mark Wine",
        "academia": "Primall JJ"
      },
      {
        "posicao": 2,
        "nome": "Curtis schaeffer",
        "academia": "Yamasaki Academy"
      },
      {
        "posicao": 3,
        "nome": "Curtis Ianigan",
        "academia": "United BJJ"
      },
      {
        "posicao": 3,
        "nome": "Paul Filidor",
        "academia": "Sub Grappling Distrct"
      }
    ]
  },
  {
    "categoria": "adult / White / male / Heavy",
    "ranking": [
      {
        "posicao": 1,
        "nome": "Theodore Von Rocc",
        "academia": "Open Dor BJJ"
      },
      {
        "posicao": 2,
        "nome": "Gabriel Haro",
        "academia": "Sandro Batata"
      },
      {
        "posicao": 3,
        "nome": "Jason Roberts",
        "academia": "Ultimate Trainning"
      },
      {
        "posicao": 3,
        "nome": "Josh Hermanson",
        "academia": "Claudio Franca"
      }
    ]
  },
  {
    "categoria": "adult / White / male / Super Heavy",
    "ranking": [
      {
        "posicao": 1,
        "nome": "Timothy Snyder",
        "academia": "Alpha Fighting System"
      },
      {
        "posicao": 2,
        "nome": "Morri Alaya",
        "academia": "Legion Jiu-jitsu"
      },
      {
        "posicao": 3,
        "nome": "Nicholas Saavedra",
        "academia": "Cesar Gracie"
      },
      {
        "posicao": 3,
        "nome": "Tom Cardona",
        "academia": "Franco de Camargo"
      }
    ]
  },
  {
    "categoria": "adult / White / male / Ultra Heavy",
    "ranking": [
      {
        "posicao": 1,
        "nome": "Chad Martin",
        "academia": "Cesar Gracie"
      },
      {
        "posicao": 2,
        "nome": "Rene Sicrre",
        "academia": "Ralph Gracie"
      },
      {
        "posicao": 3,
        "nome": "Joey Collins",
        "academia": "Alliance"
      },
      {
        "posicao": 3,
        "nome": "Garret Landry",
        "academia": "Lake Area BJJ"
      }
    ]
  },
  {
    "categoria": "adult / White / female / Light Feather",
    "ranking": [
      {
        "posicao": 1,
        "nome": "Camille Evans",
        "academia": "Elite"
      },
      {
        "posicao": 2,
        "nome": "Khunvanary Vong",
        "academia": "Brazilian Top Team"
      },
      {
        "posicao": 3,
        "nome": "Melinda Beaumont",
        "academia": "Championship Karate"
      },
      {
        "posicao": 3,
        "nome": "Ann Marjorie",
        "academia": "X-treme Jiu-Jitsu"
      }
    ]
  },
  {
    "categoria": "adult / White / female / Feather",
    "ranking": [
      {
        "posicao": 1,
        "nome": "Sarah Silva",
        "academia": "Saulo Ribeiro"
      },
      {
        "posicao": 2,
        "nome": "Laura Cook",
        "academia": "Team Mica"
      },
      {
        "posicao": 3,
        "nome": "Sarah Rendon",
        "academia": "Ricardo Barros JJ"
      },
      {
        "posicao": 3,
        "nome": "Brandi Creason",
        "academia": "Big John McCarthy"
      }
    ]
  },
  {
    "categoria": "adult / White / female / Light",
    "ranking": [
      {
        "posicao": 1,
        "nome": "Danielle Battiato",
        "academia": "Rickson"
      },
      {
        "posicao": 2,
        "nome": "Sara Sjoberg",
        "academia": "Vasteras Bjj Team"
      },
      {
        "posicao": 3,
        "nome": "Julia Voss",
        "academia": "El Passo Jiu-Jitsu"
      }
    ]
  },
  {
    "categoria": "adult / White / female / Middle",
    "ranking": [
      {
        "posicao": 1,
        "nome": "Anna Stankiewicz",
        "academia": "Alliance"
      },
      {
        "posicao": 2,
        "nome": "Melissa Dixon",
        "academia": "Megaton"
      },
      {
        "posicao": 3,
        "nome": "Jessie Peterson",
        "academia": "Saulo Ribeiro"
      },
      {
        "posicao": 3,
        "nome": "Allison Sadowski",
        "academia": "Gracie Barra"
      }
    ]
  },
  {
    "categoria": "adult / White / female / Medium Heavy",
    "ranking": [
      {
        "posicao": 1,
        "nome": "Sarah Draht",
        "academia": "Shuswap BJJ"
      },
      {
        "posicao": 2,
        "nome": "Melissa New",
        "academia": "Big John McCarthy"
      },
      {
        "posicao": 3,
        "nome": "Maria Sinoy",
        "academia": "Tinguinha"
      },
      {
        "posicao": 3,
        "nome": "Leah Mancillas",
        "academia": "LA Boxing"
      }
    ]
  },
  {
    "categoria": "Master 1 / White / Male / Light Feather",
    "ranking": [
      {
        "posicao": 1,
        "nome": "Spyros Vamvas",
        "academia": "Fight Factory Pasadena"
      },
      {
        "posicao": 2,
        "nome": "Patrick Ashley",
        "academia": "Saulo Ribeiro"
      },
      {
        "posicao": 3,
        "nome": "Ritchie Rayrao",
        "academia": "Ralph Gracie"
      },
      {
        "posicao": 3,
        "nome": "John Thompson",
        "academia": "Megaton"
      }
    ]
  },
  {
    "categoria": "Master 1 / White / Male / Feather",
    "ranking": [
      {
        "posicao": 1,
        "nome": "Sung Min cho",
        "academia": "Bervely Hills"
      },
      {
        "posicao": 2,
        "nome": "Marty Nunn",
        "academia": "Megaton"
      },
      {
        "posicao": 3,
        "nome": "Ryoki Higa",
        "academia": "Xtreme Gold Team"
      },
      {
        "posicao": 3,
        "nome": "Josh Lemos",
        "academia": "Rocha JJ"
      }
    ]
  },
  {
    "categoria": "Master 1 / White / Male / Light",
    "ranking": [
      {
        "posicao": 1,
        "nome": "Israel Campos",
        "academia": "Gracie Peru"
      },
      {
        "posicao": 2,
        "nome": "Christopher Tobias",
        "academia": "Yamasaki Academy"
      },
      {
        "posicao": 3,
        "nome": "Rod Roberts",
        "academia": "Gracie Barra"
      },
      {
        "posicao": 3,
        "nome": "John Sorrell",
        "academia": "Peninsula BJJ Pitbull"
      }
    ]
  },
  {
    "categoria": "Master 1 / White / Male / Middle",
    "ranking": [
      {
        "posicao": 1,
        "nome": "Christian Hernandez",
        "academia": "Open Dor BJJ"
      },
      {
        "posicao": 2,
        "nome": "Aaron Freeman",
        "academia": "Rickson"
      },
      {
        "posicao": 3,
        "nome": "Don Reilly",
        "academia": "Bernalles Insitute"
      },
      {
        "posicao": 3,
        "nome": "Danny Ramirez",
        "academia": "Team Mica"
      }
    ]
  },
  {
    "categoria": "Master 1 / White / Male / Medium Heavy",
    "ranking": [
      {
        "posicao": 1,
        "nome": "Scott Carman",
        "academia": "Yamasaki Academy"
      },
      {
        "posicao": 2,
        "nome": "Maxwell Smyth",
        "academia": "Megaton"
      },
      {
        "posicao": 3,
        "nome": "Raymond Gilles",
        "academia": "Marra Senki"
      },
      {
        "posicao": 3,
        "nome": "Jamie Kyler",
        "academia": "Megaton"
      }
    ]
  },
  {
    "categoria": "Master 1 / White / Male / Heavy",
    "ranking": [
      {
        "posicao": 1,
        "nome": "Sean prince",
        "academia": "Tinguinha"
      },
      {
        "posicao": 2,
        "nome": "Hector Delgado",
        "academia": "BJJ Revolution Team"
      },
      {
        "posicao": 3,
        "nome": "Luke Cozart",
        "academia": "Brazilian Top Team"
      },
      {
        "posicao": 3,
        "nome": "Kevin Leakers",
        "academia": "BJJ Revolution Team"
      }
    ]
  },
  {
    "categoria": "Master 1 / White / Male / Super Heavy",
    "ranking": [
      {
        "posicao": 1,
        "nome": "Will Link",
        "academia": "Megaton"
      },
      {
        "posicao": 2,
        "nome": "Derik Crouch",
        "academia": "Alpha Fighting System"
      },
      {
        "posicao": 3,
        "nome": "Tom Muichy",
        "academia": "Gracie Barra"
      },
      {
        "posicao": 3,
        "nome": "Sam Sade",
        "academia": "Bevely Hills JJ Club"
      }
    ]
  },
  {
    "categoria": "Master 1 / White / Male / Ultra Heavy",
    "ranking": [
      {
        "posicao": 1,
        "nome": "Matt Joyce",
        "academia": "Nova Uniao Arizona"
      },
      {
        "posicao": 2,
        "nome": "Andrew Goodman",
        "academia": "Global JJ"
      },
      {
        "posicao": 3,
        "nome": "Peter friesen",
        "academia": "Tinguinha"
      },
      {
        "posicao": 3,
        "nome": "Paul Ferreira",
        "academia": "Pedro Carvalho"
      }
    ]
  },
  {
    "categoria": "Juvenile / Blue / Male / Rooster",
    "ranking": [
      {
        "posicao": 1,
        "nome": "Keegan Byers",
        "academia": "Easton Brazilian JJ"
      },
      {
        "posicao": 2,
        "nome": "NICK Travis",
        "academia": "Gracie Barra"
      },
      {
        "posicao": 3,
        "nome": "Jason Hertzog",
        "academia": "Tatu JJ"
      }
    ]
  },
  {
    "categoria": "Juvenile / Blue / Male / Light Feather",
    "ranking": [
      {
        "posicao": 1,
        "nome": "Timmy Song",
        "academia": "Big John McCarthy"
      },
      {
        "posicao": 2,
        "nome": "Andrew Knudson",
        "academia": "Ultimate Fitness"
      },
      {
        "posicao": 3,
        "nome": "Jesse Manglona",
        "academia": "Gracie Barra"
      },
      {
        "posicao": 3,
        "nome": "Marco Batista",
        "academia": "Bervely Hills"
      }
    ]
  },
  {
    "categoria": "Juvenile / Blue / Male / Feather",
    "ranking": [
      {
        "posicao": 1,
        "nome": "Jack Wilwert",
        "academia": "Team Mica"
      },
      {
        "posicao": 2,
        "nome": "Isaac Doederlein",
        "academia": "Gracie Humaita"
      }
    ]
  },
  {
    "categoria": "Juvenile / Blue / Male / Light",
    "ranking": [
      {
        "posicao": 1,
        "nome": "Valentino Briones",
        "academia": "United BJJ"
      },
      {
        "posicao": 2,
        "nome": "matt Soliz",
        "academia": "United BJJ"
      },
      {
        "posicao": 3,
        "nome": "Brian McMahan",
        "academia": "Clube de JJ Pitbull"
      },
      {
        "posicao": 3,
        "nome": "Magd Hage",
        "academia": "Gracie Barra Culver City"
      }
    ]
  },
  {
    "categoria": "Juvenile / Blue / Male / Middle",
    "ranking": [
      {
        "posicao": 1,
        "nome": "Francisco Iturralde",
        "academia": "Alliance"
      },
      {
        "posicao": 2,
        "nome": "Hugo Gonzalez",
        "academia": "Team Mica"
      },
      {
        "posicao": 3,
        "nome": "Joshua Ruehlig",
        "academia": "Ricardo Barros JJ"
      },
      {
        "posicao": 3,
        "nome": "Tyler Eastland",
        "academia": "Yamasaki Academy"
      }
    ]
  },
  {
    "categoria": "Juvenile / Blue / Male / Medium Heavy",
    "ranking": [
      {
        "posicao": 1,
        "nome": "Cory Graham",
        "academia": "Ralph Gracie"
      },
      {
        "posicao": 2,
        "nome": "Richard Tugaoen",
        "academia": "Genesis Mat Sports"
      },
      {
        "posicao": 3,
        "nome": "Vann Slatter",
        "academia": "Claudio Franca"
      }
    ]
  },
  {
    "categoria": "Juvenile / Blue / Male / Heavy",
    "ranking": [
      {
        "posicao": 1,
        "nome": "Guilherme de Lima",
        "academia": "Team Mica"
      },
      {
        "posicao": 2,
        "nome": "Vitor Pires",
        "academia": "Legion Jiu-jitsu"
      },
      {
        "posicao": 3,
        "nome": "Jordan Huston",
        "academia": "Megaton"
      },
      {
        "posicao": 3,
        "nome": "Alex Morono",
        "academia": "Elite"
      }
    ]
  },
  {
    "categoria": "Juvenile / Blue / Male / Super Heavy",
    "ranking": [
      {
        "posicao": 1,
        "nome": "Matt Kirby",
        "academia": "Alliance"
      },
      {
        "posicao": 2,
        "nome": "Guilherme Jose",
        "academia": "Xtreme Gold Team"
      }
    ]
  },
  {
    "categoria": "Juvenile / Blue / Male / Ultra Heavy",
    "ranking": [
      {
        "posicao": 1,
        "nome": "Thomas Hingano",
        "academia": "Open Dor BJJ"
      },
      {
        "posicao": 2,
        "nome": "Daniel Garcia",
        "academia": "Aloisio Silva"
      }
    ]
  },
  {
    "categoria": "Juvenile / Blue / Male / Open Class",
    "ranking": [
      {
        "posicao": 1,
        "nome": "Thomas Hingano",
        "academia": "Open Dor BJJ"
      },
      {
        "posicao": 2,
        "nome": "Matt Kirby",
        "academia": "Alliance"
      },
      {
        "posicao": 3,
        "nome": "Joshua Ruehlig",
        "academia": "Ricardo Barros JJ"
      },
      {
        "posicao": 3,
        "nome": "dylan Owen",
        "academia": "Keith Owen Bjj"
      }
    ]
  },
  {
    "categoria": "Juvenile / Blue / Female / Middle",
    "ranking": [
      {
        "posicao": 1,
        "nome": "Ana Moreno",
        "academia": "Team Mica"
      }
    ]
  },
  {
    "categoria": "Juvenile / Blue / Female / Medium Heavy",
    "ranking": [
      {
        "posicao": 1,
        "nome": "Nicole Horton",
        "academia": "Rodrigo Teixeira"
      },
      {
        "posicao": 2,
        "nome": "Abigail Diaz",
        "academia": "Team Mica"
      }
    ]
  },
  {
    "categoria": "Adult / Blue / Male / Rooster",
    "ranking": [
      {
        "posicao": 1,
        "nome": "Thiago Saldanha Silva",
        "academia": "Renzo Gracie"
      },
      {
        "posicao": 2,
        "nome": "Joseph Creedon",
        "academia": "Relson Gracie"
      },
      {
        "posicao": 3,
        "nome": "Peter Yang",
        "academia": "Tinguinha"
      },
      {
        "posicao": 3,
        "nome": "Michael Ng-Chie",
        "academia": "Clan Gracie Barra"
      }
    ]
  },
  {
    "categoria": "Adult / Blue / Male / Light Feather",
    "ranking": [
      {
        "posicao": 1,
        "nome": "Patrick Runez",
        "academia": "Nova Uniao"
      },
      {
        "posicao": 2,
        "nome": "Jeffrey Jones",
        "academia": "Hassett's JJ"
      },
      {
        "posicao": 3,
        "nome": "Paul Ambriz",
        "academia": "Balance"
      },
      {
        "posicao": 3,
        "nome": "Kenny Savercoow",
        "academia": "Balance"
      }
    ]
  },
  {
    "categoria": "Adult / Blue / Male / Feather",
    "ranking": [
      {
        "posicao": 1,
        "nome": "Matt Sanches",
        "academia": "Ultimate Fitness"
      },
      {
        "posicao": 2,
        "nome": "Andy Main",
        "academia": "Renzo Gracie"
      },
      {
        "posicao": 3,
        "nome": "Johnny Queiroz",
        "academia": "Knuckleup"
      },
      {
        "posicao": 3,
        "nome": "Johnatan Queiroz",
        "academia": "Knuckleup"
      }
    ]
  },
  {
    "categoria": "Adult / Blue / Male / Light",
    "ranking": [
      {
        "posicao": 1,
        "nome": "David Bass",
        "academia": "Alliance"
      },
      {
        "posicao": 2,
        "nome": "Newton Casemiro",
        "academia": "Ralph Gracie"
      },
      {
        "posicao": 3,
        "nome": "Peter Runez",
        "academia": "Peak performance"
      },
      {
        "posicao": 3,
        "nome": "Danny Midell",
        "academia": "Rodrigo Medeiros"
      }
    ]
  },
  {
    "categoria": "Adult / Blue / Male / Middle",
    "ranking": [
      {
        "posicao": 1,
        "nome": "Lucas Rocha",
        "academia": "Gracie Barra"
      },
      {
        "posicao": 2,
        "nome": "Ky Hollenbeck",
        "academia": "Clan Gracie Barra"
      },
      {
        "posicao": 3,
        "nome": "Brian Morizi",
        "academia": "Gracie Barra Del Mar"
      },
      {
        "posicao": 3,
        "nome": "Damian Blazy",
        "academia": "Leo Dalla"
      }
    ]
  },
  {
    "categoria": "Adult / Blue / Male / Medium Heavy",
    "ranking": [
      {
        "posicao": 1,
        "nome": "James Holmes",
        "academia": "Alliance"
      },
      {
        "posicao": 2,
        "nome": "Rick Gamboa",
        "academia": "Fight Factory Pasadena"
      },
      {
        "posicao": 3,
        "nome": "lucas Hodges",
        "academia": "Nova Uniao Arizona"
      },
      {
        "posicao": 3,
        "nome": "Olsegun Williams",
        "academia": "Charles Gracie"
      }
    ]
  },
  {
    "categoria": "Adult / Blue / Male / Heavy",
    "ranking": [
      {
        "posicao": 1,
        "nome": "Jesse Fobes",
        "academia": "Nova Uniao"
      },
      {
        "posicao": 2,
        "nome": "Donald Bailey",
        "academia": "Franco de Camargo"
      },
      {
        "posicao": 3,
        "nome": "Mark Bondoc",
        "academia": "Gracie Barra Escondido"
      },
      {
        "posicao": 3,
        "nome": "Chris engle",
        "academia": "Team Mica"
      }
    ]
  },
  {
    "categoria": "Adult / Blue / Male / Super Heavy",
    "ranking": [
      {
        "posicao": 1,
        "nome": "Jason Parry",
        "academia": "Gracie Barra"
      },
      {
        "posicao": 2,
        "nome": "Micha Reiss",
        "academia": "Budokan"
      },
      {
        "posicao": 3,
        "nome": "Kevin Lutz",
        "academia": "Balance"
      },
      {
        "posicao": 3,
        "nome": "Chris Liaskos",
        "academia": "BJJ Revolution Team"
      }
    ]
  },
  {
    "categoria": "Adult / Blue / Male / Ultra Heavy",
    "ranking": [
      {
        "posicao": 1,
        "nome": "David Kohl",
        "academia": "Alliance"
      },
      {
        "posicao": 2,
        "nome": "Mychael Clarck",
        "academia": "Pedro Soriano"
      },
      {
        "posicao": 3,
        "nome": "Murillo Andres",
        "academia": "BJJ Revolution Team"
      },
      {
        "posicao": 3,
        "nome": "Brian Mailhot",
        "academia": "Academy of Mixade"
      }
    ]
  },
  {
    "categoria": "Adult / Blue / Female / Light Feather",
    "ranking": [
      {
        "posicao": 1,
        "nome": "Mei Yamaguchi",
        "academia": "Max Jiu-Jitsu Academy"
      },
      {
        "posicao": 2,
        "nome": "Tonya Mininger",
        "academia": "Saulo Ribeiro"
      },
      {
        "posicao": 3,
        "nome": "Erin Moran",
        "academia": "David Viera Bjj"
      },
      {
        "posicao": 3,
        "nome": "Cassandra Magdaleno",
        "academia": "Vaghi Martial Arts"
      }
    ]
  },
  {
    "categoria": "Adult / Blue / Female / Feather",
    "ranking": [
      {
        "posicao": 1,
        "nome": "Kiri Liao",
        "academia": "Valente JJ"
      },
      {
        "posicao": 2,
        "nome": "Melissa Lopes",
        "academia": "Capital Jiu-Jitsu Team"
      },
      {
        "posicao": 3,
        "nome": "Samantha Faulhaber",
        "academia": "Saulo Ribeiro"
      },
      {
        "posicao": 3,
        "nome": "Annie Middleton",
        "academia": "Megaton Oregon"
      }
    ]
  },
  {
    "categoria": "Adult / Blue / Female / Light",
    "ranking": [
      {
        "posicao": 1,
        "nome": "Angela Wilson",
        "academia": "White Tiger"
      },
      {
        "posicao": 2,
        "nome": "Jennifer Takos",
        "academia": "Lotus Club"
      }
    ]
  },
  {
    "categoria": "Adult / Blue / Female / Middle",
    "ranking": [
      {
        "posicao": 1,
        "nome": "Hillary Williams",
        "academia": "Westside JJ"
      },
      {
        "posicao": 2,
        "nome": "Nayeli Espinoza",
        "academia": "Team Mica"
      },
      {
        "posicao": 3,
        "nome": "Adrienne Adams",
        "academia": "Yamasaki Academy"
      },
      {
        "posicao": 3,
        "nome": "Nichole Decker",
        "academia": "Lloyd Irvin"
      }
    ]
  },
  {
    "categoria": "Adult / Blue / Female / Medium Heavy",
    "ranking": [
      {
        "posicao": 1,
        "nome": "Tammy Griego",
        "academia": "Gracie Barra"
      },
      {
        "posicao": 2,
        "nome": "Julia O'Riordan",
        "academia": "Easton Brazilian JJ"
      },
      {
        "posicao": 3,
        "nome": "Kay Stephenson",
        "academia": "Renzo Gracie"
      },
      {
        "posicao": 3,
        "nome": "Sara Tumbarello",
        "academia": "Guerrilla JJ"
      }
    ]
  },
  {
    "categoria": "Master / Blue / Male / Light Feather",
    "ranking": [
      {
        "posicao": 1,
        "nome": "Nguyen Hoang",
        "academia": "Kimura BH"
      },
      {
        "posicao": 2,
        "nome": "Keith Trader",
        "academia": "Saulo Ribeiro"
      },
      {
        "posicao": 3,
        "nome": "Isaac Magdaleno",
        "academia": "Vaghi Martial Arts"
      },
      {
        "posicao": 3,
        "nome": "Joji Horil",
        "academia": "Paraestra"
      }
    ]
  },
  {
    "categoria": "Master / Blue / Male / Feather",
    "ranking": [
      {
        "posicao": 1,
        "nome": "Israel Sanches",
        "academia": "Brazilian Top Team"
      },
      {
        "posicao": 2,
        "nome": "Tibor Petho",
        "academia": "Alpha Fighting System"
      },
      {
        "posicao": 3,
        "nome": "Israel Gettinger",
        "academia": "Baltimore Bjj"
      },
      {
        "posicao": 3,
        "nome": "Aaron Collins",
        "academia": "Gracie Barra San Diego"
      }
    ]
  },
  {
    "categoria": "Master / Blue / Male / Light",
    "ranking": [
      {
        "posicao": 1,
        "nome": "Charles Martone",
        "academia": "Street Sports"
      },
      {
        "posicao": 2,
        "nome": "Lawrence Pham",
        "academia": "Boran JJ"
      },
      {
        "posicao": 3,
        "nome": "Sanchez Stanfield",
        "academia": "Martial Arts USA"
      },
      {
        "posicao": 3,
        "nome": "Shaw Eichelbergen",
        "academia": "BJJ Revolution Team"
      }
    ]
  },
  {
    "categoria": "Master / Blue / Male / Middle",
    "ranking": [
      {
        "posicao": 1,
        "nome": "Joshua Webb",
        "academia": "Megaton"
      },
      {
        "posicao": 2,
        "nome": "James Shook",
        "academia": "Alpha Fighting System"
      },
      {
        "posicao": 3,
        "nome": "Brian Franklin",
        "academia": "Gracie Barra San Diego"
      },
      {
        "posicao": 3,
        "nome": "Austin Dean",
        "academia": "Knuckleup"
      },
      {
        "posicao": 3,
        "nome": "Dan Kim",
        "academia": "DM Jiu-Jitsu Academy"
      }
    ]
  },
  {
    "categoria": "Master / Blue / Male / Medium Heavy",
    "ranking": [
      {
        "posicao": 1,
        "nome": "Shannon Young",
        "academia": "Ricardo Barros JJ"
      },
      {
        "posicao": 2,
        "nome": "Gilerto Castro",
        "academia": "Maui Jiu-Jitsu"
      },
      {
        "posicao": 3,
        "nome": "Fred Zebley",
        "academia": "Alliance"
      },
      {
        "posicao": 3,
        "nome": "Cesar Aguero",
        "academia": "Machado JJ"
      }
    ]
  },
  {
    "categoria": "Master / Blue / Male / Heavy",
    "ranking": [
      {
        "posicao": 1,
        "nome": "Nicholas Knight",
        "academia": "Cia Paulista"
      },
      {
        "posicao": 2,
        "nome": "Welch Donald",
        "academia": "Lake Area BJJ"
      },
      {
        "posicao": 3,
        "nome": "James Davis",
        "academia": "Gracie Barra Northshore"
      },
      {
        "posicao": 3,
        "nome": "Wilbert Moore",
        "academia": "Gracie Barra Nederland"
      }
    ]
  },
  {
    "categoria": "Master / Blue / Male / Super Heavy",
    "ranking": [
      {
        "posicao": 1,
        "nome": "Trevin Raak",
        "academia": "Lotus Club"
      },
      {
        "posicao": 2,
        "nome": "Luke Eckart",
        "academia": "Ricardo Almeida JJ"
      },
      {
        "posicao": 3,
        "nome": "Anthony Carlson",
        "academia": "Vaghi Martial Arts"
      },
      {
        "posicao": 3,
        "nome": "Matthen Benner",
        "academia": "Gracie Barra San Diego"
      }
    ]
  },
  {
    "categoria": "Master / Blue / Male / Ultra Heavy",
    "ranking": [
      {
        "posicao": 1,
        "nome": "Wauriman Borges",
        "academia": "Clube de JJ Pitbull"
      },
      {
        "posicao": 2,
        "nome": "Kelly Gray",
        "academia": "Team Mica"
      },
      {
        "posicao": 3,
        "nome": "Griffth Sombke",
        "academia": "Gracie Barra Ballard"
      },
      {
        "posicao": 3,
        "nome": "Kohl Kaminski",
        "academia": "Jacksonville Bjj G Barra"
      }
    ]
  },
  {
    "categoria": "Master / Blue / Male / Open Class",
    "ranking": [
      {
        "posicao": 1,
        "nome": "Kelly Gray",
        "academia": "Team Mica"
      },
      {
        "posicao": 2,
        "nome": "Wauriman Borges",
        "academia": "Clube de JJ Pitbull"
      },
      {
        "posicao": 3,
        "nome": "Aaron Davis",
        "academia": "Lake Area BJJ"
      },
      {
        "posicao": 3,
        "nome": "Raszel Carpenter",
        "academia": "Triumph"
      }
    ]
  },
  {
    "categoria": "Master 2 / Blue / Male / Rooster",
    "ranking": [
      {
        "posicao": 1,
        "nome": "Paul Chong",
        "academia": "John Machado JJ"
      },
      {
        "posicao": 2,
        "nome": "Gene Gordy",
        "academia": "Gracie Barra CSRA"
      }
    ]
  },
  {
    "categoria": "Master 2 / Blue / Male / Light Feather",
    "ranking": [
      {
        "posicao": 1,
        "nome": "Keith Parknow",
        "academia": "Yamasaki Academy"
      },
      {
        "posicao": 2,
        "nome": "Yutaka Takahashi",
        "academia": "Max Jiu-Jitsu Academy"
      },
      {
        "posicao": 3,
        "nome": "Mohsen",
        "academia": "Star JJ"
      },
      {
        "posicao": 3,
        "nome": "Robin Black",
        "academia": "Saulo Ribeiro"
      }
    ]
  },
  {
    "categoria": "Master 2 / Blue / Male / Feather",
    "ranking": [
      {
        "posicao": 1,
        "nome": "James Peterson",
        "academia": "Vaghi Martial Arts"
      },
      {
        "posicao": 2,
        "nome": "Daryl Fort",
        "academia": "Cesar Gracie"
      },
      {
        "posicao": 3,
        "nome": "Avi Gazit",
        "academia": "Flavio Behring"
      },
      {
        "posicao": 3,
        "nome": "Daniel St-Amand",
        "academia": "Shuswap BJJ"
      }
    ]
  },
  {
    "categoria": "Master 2 / Blue / Male / Light",
    "ranking": [
      {
        "posicao": 1,
        "nome": "Joe Solis",
        "academia": "Neutral Grounds"
      },
      {
        "posicao": 2,
        "nome": "Randy Eckert",
        "academia": "Saulo Ribeiro"
      },
      {
        "posicao": 3,
        "nome": "Dudu Mazzocato",
        "academia": "Ralph Gracie"
      },
      {
        "posicao": 3,
        "nome": "Franklin Quenga",
        "academia": "Brazilian Top Team"
      }
    ]
  },
  {
    "categoria": "Master 2 / Blue / Male / Middle",
    "ranking": [
      {
        "posicao": 1,
        "nome": "David Leon",
        "academia": "Tinguinha"
      },
      {
        "posicao": 2,
        "nome": "Douglas Music",
        "academia": "Gracie Barra Tampa"
      },
      {
        "posicao": 3,
        "nome": "Jesse Hughes",
        "academia": "Gracie Barra America"
      },
      {
        "posicao": 3,
        "nome": "Jordan Robinson",
        "academia": "Cassio Werneck"
      }
    ]
  },
  {
    "categoria": "Master 2 / Blue / Male / Medium Heavy",
    "ranking": [
      {
        "posicao": 1,
        "nome": "Eduardo Carrasco",
        "academia": "Rey Diogo"
      },
      {
        "posicao": 2,
        "nome": "Ozzy Dilimma",
        "academia": "Team Mica"
      },
      {
        "posicao": 3,
        "nome": "Paul Haben",
        "academia": "Marra Senki"
      },
      {
        "posicao": 3,
        "nome": "Jason Martin",
        "academia": "DMA/Simmler Bjj"
      }
    ]
  },
  {
    "categoria": "Master 2 / Blue / Male / Heavy",
    "ranking": [
      {
        "posicao": 1,
        "nome": "Kurt Richardson",
        "academia": "Vaghi Martial Arts"
      },
      {
        "posicao": 2,
        "nome": "Efren Martin",
        "academia": "Gracie JJ Academy"
      },
      {
        "posicao": 3,
        "nome": "Samuel Kirk",
        "academia": "Lotus Club"
      },
      {
        "posicao": 3,
        "nome": "Salvador Flores",
        "academia": "BJJ Revolution Team"
      }
    ]
  },
  {
    "categoria": "Master 2 / Blue / Male / Super Heavy",
    "ranking": [
      {
        "posicao": 1,
        "nome": "Matthew omstein",
        "academia": "Alliance"
      },
      {
        "posicao": 2,
        "nome": "Thomas Ritter",
        "academia": "Aloisio Silva"
      },
      {
        "posicao": 3,
        "nome": "Joe Pasko",
        "academia": "Zingano BJJ"
      },
      {
        "posicao": 3,
        "nome": "JP Donahue",
        "academia": "Brazilian Top Team"
      }
    ]
  },
  {
    "categoria": "Master 2 / Blue / Male / Ultra Heavy",
    "ranking": [
      {
        "posicao": 1,
        "nome": "Harold Jones",
        "academia": "BJJ Revolution Team"
      },
      {
        "posicao": 2,
        "nome": "Michael Romero",
        "academia": "The Ultima"
      },
      {
        "posicao": 3,
        "nome": "Jose Andrade",
        "academia": "Rodrigo Teixeira"
      },
      {
        "posicao": 3,
        "nome": "Matthew Owen",
        "academia": "Keith Owen Bjj"
      }
    ]
  },
  {
    "categoria": "Master 2 / Blue / Male / Open Class",
    "ranking": [
      {
        "posicao": 1,
        "nome": "Harold Jones",
        "academia": "BJJ Revolution Team"
      },
      {
        "posicao": 2,
        "nome": "Hector Carpio",
        "academia": "Rey Diogo"
      },
      {
        "posicao": 3,
        "nome": "Eduardo carraco",
        "academia": "Rey Diogo"
      },
      {
        "posicao": 3,
        "nome": "Scott Blake",
        "academia": "Pedro Sauer"
      }
    ]
  },
  {
    "categoria": "Master 3 / Blue / Male / Light Feather",
    "ranking": [
      {
        "posicao": 1,
        "nome": "Anson Maglasang",
        "academia": "R.Minter Bjj Concepts"
      },
      {
        "posicao": 2,
        "nome": "Michael Dykes",
        "academia": "Gracie Barra"
      }
    ]
  },
  {
    "categoria": "Master 3 / Blue / Male / Feather",
    "ranking": [
      {
        "posicao": 1,
        "nome": "Andrew Culbreth",
        "academia": "Team Roc"
      }
    ]
  },
  {
    "categoria": "Master 3 / Blue / Male / Light",
    "ranking": [
      {
        "posicao": 1,
        "nome": "Mark Spray",
        "academia": "Gracie Humaita"
      },
      {
        "posicao": 2,
        "nome": "Sam DiMaggio",
        "academia": "Gracie JJ Academy"
      },
      {
        "posicao": 3,
        "nome": "Dale Kersting",
        "academia": "Gracie Humaita"
      },
      {
        "posicao": 3,
        "nome": "Eric Schuettenberg",
        "academia": "Vaghi Martial Arts"
      }
    ]
  },
  {
    "categoria": "Master 3 / Blue / Male / Middle",
    "ranking": [
      {
        "posicao": 1,
        "nome": "Mark Simmerman",
        "academia": "Brasa"
      },
      {
        "posicao": 2,
        "nome": "David Fogle",
        "academia": "Clube de JJ Pitbull"
      },
      {
        "posicao": 3,
        "nome": "David Patack",
        "academia": "Alliance"
      }
    ]
  },
  {
    "categoria": "Master 3 / Blue / Male / Medium Heavy",
    "ranking": [
      {
        "posicao": 1,
        "nome": "Carlos Sanchez",
        "academia": "Paixao JJ"
      },
      {
        "posicao": 2,
        "nome": "Joe Solorio",
        "academia": "The Ultima"
      },
      {
        "posicao": 3,
        "nome": "Paul Kelley",
        "academia": "Kazeka Bjj"
      },
      {
        "posicao": 3,
        "nome": "Gustavo Naranjo",
        "academia": "Lotus Club"
      }
    ]
  },
  {
    "categoria": "Master 3 / Blue / Male / Heavy",
    "ranking": [
      {
        "posicao": 1,
        "nome": "Ray Campos",
        "academia": "Gracie Barra"
      },
      {
        "posicao": 2,
        "nome": "Thomas Rice",
        "academia": "Jungle Fight Team"
      },
      {
        "posicao": 3,
        "nome": "Norman Ayers",
        "academia": "Gracie Humaita"
      },
      {
        "posicao": 3,
        "nome": "Bart Bosler",
        "academia": "Star JJ"
      }
    ]
  },
  {
    "categoria": "Master 3 / Blue / Male / Super Heavy",
    "ranking": [
      {
        "posicao": 1,
        "nome": "John Bailey",
        "academia": "Alliance"
      },
      {
        "posicao": 2,
        "nome": "Mark Brown",
        "academia": "Carlson Gracie Team"
      },
      {
        "posicao": 3,
        "nome": "Michael Bush",
        "academia": "Jungle Fight Team"
      }
    ]
  },
  {
    "categoria": "Master 3 / Blue / Male / Ultra Heavy",
    "ranking": [
      {
        "posicao": 1,
        "nome": "Jeff Moffet",
        "academia": "Kazeka Bjj"
      },
      {
        "posicao": 2,
        "nome": "Glenn Parker",
        "academia": "Rey Diogo"
      }
    ]
  },
  {
    "categoria": "Master 3 / Blue / Male / Open Class",
    "ranking": [
      {
        "posicao": 1,
        "nome": "Thomas Rice",
        "academia": "Jungle Fight Team"
      },
      {
        "posicao": 1,
        "nome": "Jeff Moffet",
        "academia": "Kazeka Bjj"
      },
      {
        "posicao": 3,
        "nome": "Joe Selonio",
        "academia": "The Ultima"
      },
      {
        "posicao": 3,
        "nome": "Jaime Alvarengo",
        "academia": "Pitbull"
      }
    ]
  },
  {
    "categoria": "Master 4 / Blue / Male / Feather",
    "ranking": [
      {
        "posicao": 1,
        "nome": "Raimundo",
        "academia": "Saulo Ribeiro"
      },
      {
        "posicao": 2,
        "nome": "Duane Ittner",
        "academia": "Minesota Martial Arts"
      }
    ]
  },
  {
    "categoria": "Master 4 / Blue / Male / Light",
    "ranking": [
      {
        "posicao": 1,
        "nome": "Delano Vincent",
        "academia": "BJJ Revolution Team"
      }
    ]
  },
  {
    "categoria": "Master 4 / Blue / Male / Middle",
    "ranking": [
      {
        "posicao": 1,
        "nome": "Brian Beauchamp",
        "academia": "Fabricio"
      },
      {
        "posicao": 2,
        "nome": "Eduardo Cagnin",
        "academia": "Rillion Gracie"
      },
      {
        "posicao": 3,
        "nome": "Thomas Dwyer",
        "academia": "Gracie Barra Encinitas"
      },
      {
        "posicao": 3,
        "nome": "Joseph Thompson",
        "academia": "Soca BJJ"
      }
    ]
  },
  {
    "categoria": "Master 4 / Blue / Male / Medium Heavy",
    "ranking": [
      {
        "posicao": 1,
        "nome": "James Oleson",
        "academia": "Gracie Barra Escondido"
      },
      {
        "posicao": 2,
        "nome": "Hugh Rochford",
        "academia": "Gazze Academy"
      },
      {
        "posicao": 3,
        "nome": "Raymond Winters",
        "academia": "Sergio Penha JJ"
      },
      {
        "posicao": 3,
        "nome": "Ron Rose",
        "academia": "Shuswap BJJ"
      }
    ]
  },
  {
    "categoria": "Master 4 / Blue / Male / Heavy",
    "ranking": [
      {
        "posicao": 1,
        "nome": "Stephen Fulton",
        "academia": "Gracie JJ Academy"
      },
      {
        "posicao": 2,
        "nome": "Tomothy Rourke",
        "academia": "Academy of Mixade"
      },
      {
        "posicao": 3,
        "nome": "Murilo Vasconcelos",
        "academia": "Alliance"
      },
      {
        "posicao": 3,
        "nome": "Pedro Diaz",
        "academia": "Nova Uniao"
      }
    ]
  },
  {
    "categoria": "Master 4 / Blue / Male / Super Heavy",
    "ranking": [
      {
        "posicao": 1,
        "nome": "Adobin Schroth",
        "academia": "Brazilian Jiu-Jitsu Club"
      }
    ]
  },
  {
    "categoria": "Master 4 / Blue / Male / Ultra Heavy",
    "ranking": [
      {
        "posicao": 1,
        "nome": "Doug Muhle",
        "academia": "Team Roc"
      },
      {
        "posicao": 2,
        "nome": "Glen Gorss",
        "academia": "Alliance"
      },
      {
        "posicao": 3,
        "nome": "Mathew Doty",
        "academia": "Gracie Barra San"
      }
    ]
  },
  {
    "categoria": "Master 4 / Blue / Male / Open Class",
    "ranking": [
      {
        "posicao": 1,
        "nome": "Mathew Doty",
        "academia": "Gracie Barra San"
      },
      {
        "posicao": 2,
        "nome": "Doug Muhle",
        "academia": "Team Roc"
      },
      {
        "posicao": 3,
        "nome": "Pedro dias",
        "academia": "Nova Uniao"
      }
    ]
  },
  {
    "categoria": "Adult / Purple / Male / Light Feather",
    "ranking": [
      {
        "posicao": 1,
        "nome": "Remco Van Baardewijk",
        "academia": "Team Agua"
      },
      {
        "posicao": 2,
        "nome": "Mark Ramos",
        "academia": "Edson Carvalho"
      },
      {
        "posicao": 3,
        "nome": "Colin Beauregard",
        "academia": "BJJ Revolution Team"
      }
    ]
  },
  {
    "categoria": "Adult / Purple / Male / Feather",
    "ranking": [
      {
        "posicao": 1,
        "nome": "Zak Maxwell",
        "academia": "Saulo Ribeiro"
      },
      {
        "posicao": 2,
        "nome": "Brendan Guccione",
        "academia": "Gracie Barra"
      },
      {
        "posicao": 3,
        "nome": "Kuanggyan Huang",
        "academia": "BJJ Revolution Team"
      },
      {
        "posicao": 3,
        "nome": "Merick Hamilton",
        "academia": "Cassio Werneck"
      }
    ]
  },
  {
    "categoria": "Adult / Purple / Male / Light",
    "ranking": [
      {
        "posicao": 1,
        "nome": "Jacob Mackenzie",
        "academia": "Akxe BJJ"
      },
      {
        "posicao": 2,
        "nome": "Chace Wheaton",
        "academia": "Alliance"
      },
      {
        "posicao": 3,
        "nome": "Takuma Wakabayashi",
        "academia": "Max Jiu-Jitsu Academy"
      },
      {
        "posicao": 3,
        "nome": "Choi Choi",
        "academia": "Renzo Gracie"
      }
    ]
  },
  {
    "categoria": "Adult / Purple / Male / Middle",
    "ranking": [
      {
        "posicao": 1,
        "nome": "Jose Carlos Silva",
        "academia": "DDR Jiu-Jitsu"
      },
      {
        "posicao": 2,
        "nome": "Eduardo Zanetti",
        "academia": "Gracie Barra"
      },
      {
        "posicao": 3,
        "nome": "Warren Atout",
        "academia": "Hollywood Bjj"
      },
      {
        "posicao": 3,
        "nome": "Alec Balding",
        "academia": "Alliance"
      }
    ]
  },
  {
    "categoria": "Adult / Purple / Male / Medium Heavy",
    "ranking": [
      {
        "posicao": 1,
        "nome": "Antonio Antonioli",
        "academia": "Sul JJ"
      },
      {
        "posicao": 2,
        "nome": "Matt Sloan",
        "academia": "Megaton"
      },
      {
        "posicao": 3,
        "nome": "Marcel Peixoto",
        "academia": "Ralph Gracie"
      }
    ]
  },
  {
    "categoria": "Adult / Purple / Male / Heavy",
    "ranking": [
      {
        "posicao": 1,
        "nome": "Jack Shellenberger",
        "academia": "Saulo Ribeiro"
      },
      {
        "posicao": 2,
        "nome": "James Puopol",
        "academia": "Megaton"
      },
      {
        "posicao": 3,
        "nome": "Frederick Ramie",
        "academia": "Gracie Barra"
      },
      {
        "posicao": 3,
        "nome": "Antonio Salvador",
        "academia": "Tinguinha"
      },
      {
        "posicao": 3,
        "nome": "Steven olivier",
        "academia": "NYMAG"
      }
    ]
  },
  {
    "categoria": "Adult / Purple / Male / Super Heavy",
    "ranking": [
      {
        "posicao": 1,
        "nome": "Neiman Gracie",
        "academia": "Gracie Barra"
      },
      {
        "posicao": 2,
        "nome": "Jason Spallek",
        "academia": "Zingano BJJ"
      },
      {
        "posicao": 3,
        "nome": "Carlos Fletes",
        "academia": "Team Mica"
      },
      {
        "posicao": 3,
        "nome": "Hazem Ibrahim",
        "academia": "Ricardo Almeida JJ"
      }
    ]
  },
  {
    "categoria": "Adult / Purple / Male / Ultra Heavy",
    "ranking": [
      {
        "posicao": 1,
        "nome": "jarrod Brunch",
        "academia": "Bervely Hills"
      },
      {
        "posicao": 2,
        "nome": "Mike Schuss",
        "academia": "Team Mica"
      },
      {
        "posicao": 3,
        "nome": "Kroyler Leao",
        "academia": "Luis Filho Team"
      },
      {
        "posicao": 3,
        "nome": "David Ashkinaz",
        "academia": "Triune JJ"
      }
    ]
  },
  {
    "categoria": "Adult / Purple / Male / Open Class",
    "ranking": [
      {
        "posicao": 1,
        "nome": "Jannod Bunch",
        "academia": "Bervely Hills"
      },
      {
        "posicao": 2,
        "nome": "Jose Carlos",
        "academia": "DDR Jiu-Jitsu"
      },
      {
        "posicao": 3,
        "nome": "Matt Sloan",
        "academia": "Megaton"
      },
      {
        "posicao": 3,
        "nome": "Marcel Goncalves",
        "academia": "Nova Geracao"
      }
    ]
  },
  {
    "categoria": "Adult / Purple / Female / Light Feather",
    "ranking": [
      {
        "posicao": 1,
        "nome": "Nyjah Easton",
        "academia": "Lloyd Irvin"
      },
      {
        "posicao": 2,
        "nome": "Naomi Walker",
        "academia": "Rickson"
      },
      {
        "posicao": 3,
        "nome": "Yasmin Sewgobind",
        "academia": "Yamasaki Academy"
      },
      {
        "posicao": 3,
        "nome": "Hillary Witt",
        "academia": "Saulo Ribeiro"
      }
    ]
  },
  {
    "categoria": "Adult / Purple / Female / Feather",
    "ranking": [
      {
        "posicao": 1,
        "nome": "Jennifer Weintz",
        "academia": "Gracie Barra"
      },
      {
        "posicao": 2,
        "nome": "Melissa Haueter",
        "academia": "Rigan Mchado"
      },
      {
        "posicao": 3,
        "nome": "Beatriz Brandao",
        "academia": "Cia Paulista"
      },
      {
        "posicao": 3,
        "nome": "Heather Schmitz",
        "academia": "Zingano BJJ"
      }
    ]
  },
  {
    "categoria": "Adult / Purple / Female / Light",
    "ranking": [
      {
        "posicao": 1,
        "nome": "Beatriz Mesquita",
        "academia": "Gracie Humaita"
      },
      {
        "posicao": 2,
        "nome": "Arnela Carmichael",
        "academia": "BJJ Revolution Team"
      },
      {
        "posicao": 3,
        "nome": "Mariana Rocha",
        "academia": "Competition"
      },
      {
        "posicao": 3,
        "nome": "NgelaHadzisulejmanovic",
        "academia": "Hilti BJJ"
      }
    ]
  },
  {
    "categoria": "Adult / Purple / Female / Medium Heavy",
    "ranking": [
      {
        "posicao": 1,
        "nome": "Katrina Weilbacher",
        "academia": "Alliance"
      },
      {
        "posicao": 1,
        "nome": "Jennifer Guiola Petterson",
        "academia": "Hilti BJJ"
      },
      {
        "posicao": 2,
        "nome": "Emily Wetzel",
        "academia": "Gracie Barra"
      },
      {
        "posicao": 2,
        "nome": "Magdalina Gofman",
        "academia": "Ralph Gracie"
      },
      {
        "posicao": 3,
        "nome": "Bethany Schulze",
        "academia": "Tiger Academy"
      },
      {
        "posicao": 3,
        "nome": "Cindy Magdaleno",
        "academia": "Caique JJ"
      },
      {
        "posicao": 3,
        "nome": "Catlin Huggins",
        "academia": "Gracie Barra"
      }
    ]
  },
  {
    "categoria": "Adult / Purple / Female / Open Class",
    "ranking": [
      {
        "posicao": 1,
        "nome": "Beatriz Mesquita",
        "academia": "Gracie Humaita"
      },
      {
        "posicao": 2,
        "nome": "Karen Miller",
        "academia": "Brasa"
      },
      {
        "posicao": 3,
        "nome": "Catlin Huggins",
        "academia": "Gracie Barra"
      },
      {
        "posicao": 3,
        "nome": "Katrina Weilbacher",
        "academia": "Alliance"
      }
    ]
  },
  {
    "categoria": "Master 1 / Purple / Male / Rooster",
    "ranking": [
      {
        "posicao": 1,
        "nome": "John Padova",
        "academia": "Saulo Ribeiro"
      },
      {
        "posicao": 2,
        "nome": "Eric Verrill",
        "academia": "Claudio Franca"
      },
      {
        "posicao": 3,
        "nome": "Alexander Taveira",
        "academia": "Gracie Barra"
      }
    ]
  },
  {
    "categoria": "Master 1 / Purple / Male / Light Feather",
    "ranking": [
      {
        "posicao": 1,
        "nome": "Jacob Gaston",
        "academia": "Nova Uniao Arizona"
      },
      {
        "posicao": 2,
        "nome": "Frank Portella",
        "academia": "Alliance"
      },
      {
        "posicao": 3,
        "nome": "Danny Swartout",
        "academia": "Megaton"
      },
      {
        "posicao": 3,
        "nome": "Tyler Vanosdell",
        "academia": "BJJ Revolution Team"
      }
    ]
  },
  {
    "categoria": "Master 1 / Purple / Male / Feather",
    "ranking": [
      {
        "posicao": 1,
        "nome": "Jason Evangelista",
        "academia": "Alpha Fighting System"
      },
      {
        "posicao": 2,
        "nome": "Daigo Takahashi",
        "academia": "Axis Japan"
      },
      {
        "posicao": 3,
        "nome": "David Boehme",
        "academia": "Gracie Humaita"
      },
      {
        "posicao": 3,
        "nome": "Gabriel Gaston",
        "academia": "Gracie Humaita/Megaton"
      }
    ]
  },
  {
    "categoria": "Master 1 / Purple / Male / Light",
    "ranking": [
      {
        "posicao": 1,
        "nome": "Michikazu Moriuchi",
        "academia": "Bervely Hills"
      },
      {
        "posicao": 2,
        "nome": "Dimitrius Chrisos",
        "academia": "BJJ Revolution Team"
      },
      {
        "posicao": 3,
        "nome": "Carlos Zapata",
        "academia": "Saulo Ribeiro"
      },
      {
        "posicao": 3,
        "nome": "Carlos Mendes",
        "academia": "Competition"
      }
    ]
  },
  {
    "categoria": "Master 1 / Purple / Male / Middle",
    "ranking": [
      {
        "posicao": 1,
        "nome": "Brian Rago",
        "academia": "Saulo Ribeiro"
      },
      {
        "posicao": 2,
        "nome": "Francis Keller",
        "academia": "BJJ Revolution Team"
      },
      {
        "posicao": 3,
        "nome": "Bob Johnson",
        "academia": "Megaton"
      },
      {
        "posicao": 3,
        "nome": "Robert Palanuk",
        "academia": "Brazilian Top Team"
      }
    ]
  },
  {
    "categoria": "Master 1 / Purple / Male / Medium Heavy",
    "ranking": [
      {
        "posicao": 1,
        "nome": "Jason Parry",
        "academia": "Carlson Gracie Team"
      },
      {
        "posicao": 2,
        "nome": "Shannon Mathers",
        "academia": "Machado Dallas"
      },
      {
        "posicao": 3,
        "nome": "Macelo Kaminski",
        "academia": "Cia Paulista"
      },
      {
        "posicao": 3,
        "nome": "Ron Hulsey",
        "academia": "Tinguinha"
      }
    ]
  },
  {
    "categoria": "Master 1 / Purple / Male / Heavy",
    "ranking": [
      {
        "posicao": 1,
        "nome": "Matheus Oliveira",
        "academia": "Lotus Club"
      },
      {
        "posicao": 2,
        "nome": "Kukric Andrej",
        "academia": "BJJ Revolution Team"
      },
      {
        "posicao": 3,
        "nome": "Jay Nance",
        "academia": "Eduardo Barros"
      },
      {
        "posicao": 3,
        "nome": "Phillip Moore",
        "academia": "BJJ Revolution Team"
      }
    ]
  },
  {
    "categoria": "Master 1 / Purple / Male / Super Heavy",
    "ranking": [
      {
        "posicao": 1,
        "nome": "Scott Morton",
        "academia": "Vaghi Martial Arts"
      },
      {
        "posicao": 2,
        "nome": "Casey Strobel",
        "academia": "Lake Area BJJ"
      },
      {
        "posicao": 3,
        "nome": "Ethan Garrison",
        "academia": "Knuckleup"
      },
      {
        "posicao": 3,
        "nome": "Matthew Rich",
        "academia": "Lotus Club"
      }
    ]
  },
  {
    "categoria": "Master 1 / Purple / Male / Ultra Heavy",
    "ranking": [
      {
        "posicao": 1,
        "nome": "Scott Olson",
        "academia": "Megaton"
      },
      {
        "posicao": 2,
        "nome": "Joel Orozco",
        "academia": "Street Sports"
      },
      {
        "posicao": 3,
        "nome": "JC Cavileer",
        "academia": "BJJ Revolution Team"
      }
    ]
  },
  {
    "categoria": "Master 1 / Purple / Male / Open Class",
    "ranking": [
      {
        "posicao": 1,
        "nome": "Brian Rayo",
        "academia": "Saulo Ribeiro"
      },
      {
        "posicao": 2,
        "nome": "Shannon Mathers",
        "academia": "Machado Dallas"
      },
      {
        "posicao": 3,
        "nome": "Jay Nance",
        "academia": "Eduardo Barros"
      },
      {
        "posicao": 3,
        "nome": "Ururahy Rodriguez",
        "academia": "Gracie Humaita"
      }
    ]
  },
  {
    "categoria": "Master 2 / Purple / Male / Light Feather",
    "ranking": [
      {
        "posicao": 1,
        "nome": "Casey Byers",
        "academia": "Easton Brazilian JJ"
      },
      {
        "posicao": 2,
        "nome": "Antonio Monhos",
        "academia": "Saulo Ribeiro"
      },
      {
        "posicao": 3,
        "nome": "Moraru Eldad",
        "academia": "Yamasaki Academy"
      }
    ]
  },
  {
    "categoria": "Master 2 / Purple / Male / Feather",
    "ranking": [
      {
        "posicao": 1,
        "nome": "Tri Nguyen",
        "academia": "Carlson Gracie Team"
      },
      {
        "posicao": 2,
        "nome": "Ken Hiley",
        "academia": "Gracie Barra Tampa"
      },
      {
        "posicao": 3,
        "nome": "Galen Tong",
        "academia": "Street Sports"
      },
      {
        "posicao": 3,
        "nome": "Gary Haver",
        "academia": "Gracie Barra"
      }
    ]
  },
  {
    "categoria": "Master 2 / Purple / Male / Light",
    "ranking": [
      {
        "posicao": 1,
        "nome": "Henry Cortez",
        "academia": "Claudio Franca"
      },
      {
        "posicao": 2,
        "nome": "Samir Karlsson",
        "academia": "Renzo Gracie"
      },
      {
        "posicao": 3,
        "nome": "Loren Allen",
        "academia": "New Mexico"
      },
      {
        "posicao": 3,
        "nome": "Elias Morris",
        "academia": "Gracie Barra Tampa"
      }
    ]
  },
  {
    "categoria": "Master 2 / Purple / Male / Middle",
    "ranking": [
      {
        "posicao": 1,
        "nome": "Scot Clontz",
        "academia": "Academy of Mixade"
      },
      {
        "posicao": 2,
        "nome": "Demian Wilamson",
        "academia": "De La Riva"
      },
      {
        "posicao": 3,
        "nome": "Vince Tran",
        "academia": "Rickson"
      },
      {
        "posicao": 3,
        "nome": "Tom Knox",
        "academia": "Cleber JJ"
      }
    ]
  },
  {
    "categoria": "Master 2 / Purple / Male / Medium Heavy",
    "ranking": [
      {
        "posicao": 1,
        "nome": "Todd Eckhardt",
        "academia": "Lotus Club"
      },
      {
        "posicao": 2,
        "nome": "Cesar Whitt",
        "academia": "Gracie Barra"
      },
      {
        "posicao": 3,
        "nome": "Joe Twumasi",
        "academia": "Gracie JJ Academy"
      }
    ]
  },
  {
    "categoria": "Master 2 / Purple / Male / Heavy",
    "ranking": [
      {
        "posicao": 1,
        "nome": "Corey Bennin",
        "academia": "Gracie Barra Oceanside"
      },
      {
        "posicao": 2,
        "nome": "Alex Orozco",
        "academia": "Tinguinha"
      },
      {
        "posicao": 3,
        "nome": "William Bouck",
        "academia": "Gracie Humaita"
      },
      {
        "posicao": 3,
        "nome": "Ira Daugherty",
        "academia": "Saulo Ribeiro"
      }
    ]
  },
  {
    "categoria": "Master 2 / Purple / Male / Super Heavy",
    "ranking": [
      {
        "posicao": 1,
        "nome": "Stephen Hall",
        "academia": "Alliance"
      },
      {
        "posicao": 2,
        "nome": "Jamie Baker",
        "academia": "Claudio Franca"
      }
    ]
  },
  {
    "categoria": "Master 2 / Purple / Male / Ultra Heavy",
    "ranking": [
      {
        "posicao": 1,
        "nome": "keita Sullivan",
        "academia": "Balance"
      }
    ]
  },
  {
    "categoria": "Master 2 / Purple / Male / Open Class",
    "ranking": [
      {
        "posicao": 1,
        "nome": "Corey Bennin",
        "academia": "Gracie Barra Oceanside"
      },
      {
        "posicao": 2,
        "nome": "Keita Sullivan",
        "academia": "Balance"
      },
      {
        "posicao": 3,
        "nome": "Stephew Hall",
        "academia": "Alliance"
      }
    ]
  },
  {
    "categoria": "Master 3 / Purple / Male / Light Feather",
    "ranking": [
      {
        "posicao": 1,
        "nome": "Derek Kaivani",
        "academia": "Alliance"
      },
      {
        "posicao": 2,
        "nome": "Greg Norsworthy",
        "academia": "Lake Area BJJ"
      }
    ]
  },
  {
    "categoria": "Master 3 / Purple / Male / Feather",
    "ranking": [
      {
        "posicao": 1,
        "nome": "Jaswant Abrescy",
        "academia": "John Machado JJ"
      }
    ]
  },
  {
    "categoria": "Master 3 / Purple / Male / Light",
    "ranking": [
      {
        "posicao": 1,
        "nome": "Joseph Sanzone",
        "academia": "Luis Filho Team"
      },
      {
        "posicao": 2,
        "nome": "David Shin",
        "academia": "Gracie Barra San Diego"
      }
    ]
  },
  {
    "categoria": "Master 3 / Purple / Male / Middle",
    "ranking": [
      {
        "posicao": 1,
        "nome": "Sina Hadad",
        "academia": "Star JJ"
      },
      {
        "posicao": 2,
        "nome": "John Burke",
        "academia": "Alliance"
      }
    ]
  },
  {
    "categoria": "Master 3 / Purple / Male / Medium Heavy",
    "ranking": [
      {
        "posicao": 1,
        "nome": "Paul Nava",
        "academia": "Nova Uniao Arizona"
      },
      {
        "posicao": 2,
        "nome": "Dwayne Bulat",
        "academia": "Laurita BJJ"
      }
    ]
  },
  {
    "categoria": "Master 3 / Purple / Male / Heavy",
    "ranking": [
      {
        "posicao": 1,
        "nome": "Neil Wolfson",
        "academia": "Soca BJJ"
      }
    ]
  },
  {
    "categoria": "Master 3 / Purple / Male / Super Heavy",
    "ranking": [
      {
        "posicao": 1,
        "nome": "Nicolai Holt",
        "academia": "Cobra Kai"
      },
      {
        "posicao": 2,
        "nome": "Bill Hotter",
        "academia": "Cesar Gracie"
      },
      {
        "posicao": 3,
        "nome": "Charles Mason",
        "academia": "Alliance"
      },
      {
        "posicao": 3,
        "nome": "Maurice Geyen",
        "academia": "Gracie Barra"
      }
    ]
  },
  {
    "categoria": "Master 3 / Purple / Male / Ultra Heavy",
    "ranking": [
      {
        "posicao": 1,
        "nome": "Rick Geist",
        "academia": "Lotus Club"
      }
    ]
  },
  {
    "categoria": "Master 3 / Purple / Male / Open Class",
    "ranking": [
      {
        "posicao": 1,
        "nome": "Nicolai Holt",
        "academia": "Cobra Kai"
      },
      {
        "posicao": 1,
        "nome": "Nicolai Holt",
        "academia": "Cobra Kai"
      },
      {
        "posicao": 2,
        "nome": "Bill Debernarder",
        "academia": "Gracie Barra"
      },
      {
        "posicao": 3,
        "nome": "Andy Arvai",
        "academia": "Gracie Barra San Diego"
      },
      {
        "posicao": 3,
        "nome": "Mario Gonzalez",
        "academia": "Gracie Barra Temecula"
      }
    ]
  },
  {
    "categoria": "Master 4 / Purple / Male / Feather",
    "ranking": [
      {
        "posicao": 1,
        "nome": "Russ Haitsuka",
        "academia": "Gazze Academy"
      },
      {
        "posicao": 2,
        "nome": "Jay Sillyman",
        "academia": "Lake Area BJJ"
      },
      {
        "posicao": 3,
        "nome": "Yasumasa Takahashi",
        "academia": "Renzo Gracie"
      }
    ]
  },
  {
    "categoria": "Master 4 / Purple / Male / Light",
    "ranking": [
      {
        "posicao": 1,
        "nome": "Greg Shen",
        "academia": "Fabio Santos"
      },
      {
        "posicao": 2,
        "nome": "Joel Goldberg",
        "academia": "Saulo Ribeiro"
      }
    ]
  },
  {
    "categoria": "Master 4 / Purple / Male / Middle",
    "ranking": [
      {
        "posicao": 1,
        "nome": "Dan Olmstead",
        "academia": "Saulo Ribeiro"
      },
      {
        "posicao": 2,
        "nome": "Mark Sausser",
        "academia": "Gustavo Machado"
      },
      {
        "posicao": 3,
        "nome": "John Bolton",
        "academia": "Gracie Barra"
      },
      {
        "posicao": 3,
        "nome": "Jim McPherson",
        "academia": "Alliance"
      }
    ]
  },
  {
    "categoria": "Master 4 / Purple / Male / Medium Heavy",
    "ranking": [
      {
        "posicao": 1,
        "nome": "Atkin Michael",
        "academia": "Lloyd Irvin"
      },
      {
        "posicao": 2,
        "nome": "Francisco Nunez",
        "academia": "Ralph Gracie"
      }
    ]
  },
  {
    "categoria": "Master 4 / Purple / Male / Heavy",
    "ranking": [
      {
        "posicao": 1,
        "nome": "Gary Casey",
        "academia": "Claudio Franca"
      },
      {
        "posicao": 2,
        "nome": "Willie Rodriguez",
        "academia": "Alliance"
      }
    ]
  },
  {
    "categoria": "Master 4 / Purple / Male / Open Class",
    "ranking": [
      {
        "posicao": 1,
        "nome": "Jim Mc Pherson",
        "academia": "Alliance"
      },
      {
        "posicao": 2,
        "nome": "Atkin Michael",
        "academia": "Lloyd Irvin"
      },
      {
        "posicao": 3,
        "nome": "Mark Sausser",
        "academia": "Gustavo Machado"
      },
      {
        "posicao": 3,
        "nome": "Willie Rodriguez",
        "academia": "Alliance"
      }
    ]
  },
  {
    "categoria": "Adult / Brown / Male / Light Feather",
    "ranking": [
      {
        "posicao": 1,
        "nome": "Alfred Thompkins",
        "academia": "Gracie Barra"
      },
      {
        "posicao": 2,
        "nome": "Hiroyuki Mizuno",
        "academia": "Alliance"
      },
      {
        "posicao": 3,
        "nome": "Demian Key",
        "academia": "Alliance"
      }
    ]
  },
  {
    "categoria": "Adult / Brown / Male / Feather",
    "ranking": [
      {
        "posicao": 1,
        "nome": "Thiago Clamente",
        "academia": "Alliance"
      },
      {
        "posicao": 2,
        "nome": "Justin Rader",
        "academia": "Saulo Ribeiro"
      },
      {
        "posicao": 3,
        "nome": "Fabricio Medici",
        "academia": "Lotus Club"
      },
      {
        "posicao": 3,
        "nome": "Gustavo Carpio",
        "academia": "Marra Senki"
      }
    ]
  },
  {
    "categoria": "Adult / Brown / Male / Light",
    "ranking": [
      {
        "posicao": 1,
        "nome": "Tiago Coelho Rocha",
        "academia": "Alliance"
      },
      {
        "posicao": 2,
        "nome": "David Hart",
        "academia": "Machado Australia"
      },
      {
        "posicao": 3,
        "nome": "Kayron Gracie",
        "academia": "Gracie Barra"
      },
      {
        "posicao": 3,
        "nome": "Steven Rosemberg",
        "academia": "Nova Uniao Arizona"
      }
    ]
  },
  {
    "categoria": "Adult / Brown / Male / Middle",
    "ranking": [
      {
        "posicao": 1,
        "nome": "Kron Gracie",
        "academia": "Rickson"
      },
      {
        "posicao": 2,
        "nome": "Marcelo Mafra",
        "academia": "Brasa"
      },
      {
        "posicao": 3,
        "nome": "Alexander Vamos",
        "academia": "D'arce Bjj"
      },
      {
        "posicao": 3,
        "nome": "Ian McPherson",
        "academia": "Alliance"
      }
    ]
  },
  {
    "categoria": "Adult / Brown / Male / Medium Heavy",
    "ranking": [
      {
        "posicao": 1,
        "nome": "Matt Jubera",
        "academia": "Saulo Ribeiro"
      },
      {
        "posicao": 2,
        "nome": "Felipe Fogolin",
        "academia": "Cleber JJ"
      },
      {
        "posicao": 3,
        "nome": "Jacob McClintock",
        "academia": "Nova Uniao Arizona"
      },
      {
        "posicao": 3,
        "nome": "Pablo Alves",
        "academia": "Gracie Barra America"
      }
    ]
  },
  {
    "categoria": "Adult / Brown / Male / Heavy",
    "ranking": [
      {
        "posicao": 1,
        "nome": "Christopher Moriarty",
        "academia": "Alliance"
      },
      {
        "posicao": 2,
        "nome": "Antonio Peinado",
        "academia": "Alliance"
      },
      {
        "posicao": 3,
        "nome": "Arman Barros",
        "academia": "Brasa"
      },
      {
        "posicao": 3,
        "nome": "Joao Assis",
        "academia": "Brasa"
      }
    ]
  },
  {
    "categoria": "Adult / Brown / Male / Super Heavy",
    "ranking": [
      {
        "posicao": 1,
        "nome": "Tom DeBlass",
        "academia": "Ricardo Almeida JJ"
      },
      {
        "posicao": 2,
        "nome": "Carlos Melo",
        "academia": "Claudio Franca"
      },
      {
        "posicao": 3,
        "nome": "Fabio Viana",
        "academia": "Cia Paulista"
      },
      {
        "posicao": 3,
        "nome": "Leonardo Iturralde",
        "academia": "Alliance"
      }
    ]
  },
  {
    "categoria": "Adult / Brown / Male / Ultra Heavy",
    "ranking": [
      {
        "posicao": 1,
        "nome": "Fabio Vilela",
        "academia": "Gracie Barra"
      },
      {
        "posicao": 2,
        "nome": "Dominic Greco",
        "academia": "Half Moon Bay Bjj"
      }
    ]
  },
  {
    "categoria": "Adult / Brown / Male / Open Class",
    "ranking": [
      {
        "posicao": 1,
        "nome": "Kron Gracie",
        "academia": "Rickson"
      },
      {
        "posicao": 2,
        "nome": "Christopher Muriarty",
        "academia": "Alliance"
      },
      {
        "posicao": 3,
        "nome": "Abmar Barbosa",
        "academia": "Brasa"
      },
      {
        "posicao": 3,
        "nome": "Antonio Peinado",
        "academia": "Alliance"
      }
    ]
  },
  {
    "categoria": "Master 1 / Brown / Male / Light Feather",
    "ranking": [
      {
        "posicao": 1,
        "nome": "Katsuyuki Nobi",
        "academia": "Alliance"
      }
    ]
  },
  {
    "categoria": "Master 1 / Brown / Male / Feather",
    "ranking": [
      {
        "posicao": 1,
        "nome": "Patrick Head",
        "academia": "Gracie Barra"
      },
      {
        "posicao": 2,
        "nome": "Scott DeWitt",
        "academia": "Jean Jacques Machado"
      },
      {
        "posicao": 3,
        "nome": "Peter Doyle",
        "academia": "Ralph Gracie"
      },
      {
        "posicao": 3,
        "nome": "Joseph Sirko",
        "academia": "Yamasaki Academy"
      }
    ]
  },
  {
    "categoria": "Master 1 / Brown / Male / Light",
    "ranking": [
      {
        "posicao": 1,
        "nome": "Joel Tudor",
        "academia": "BJJ Revolution Team"
      },
      {
        "posicao": 2,
        "nome": "Stephan Goyne",
        "academia": "Saulo Ribeiro"
      },
      {
        "posicao": 3,
        "nome": "Sam Kressin",
        "academia": "Martial Arts Life"
      },
      {
        "posicao": 3,
        "nome": "Fernando Travessoni",
        "academia": "Bervely Hills"
      }
    ]
  },
  {
    "categoria": "Master 1 / Brown / Male / Middle",
    "ranking": [
      {
        "posicao": 1,
        "nome": "Andrew Smith",
        "academia": "BJJ Revolution Team"
      },
      {
        "posicao": 2,
        "nome": "Rafael Carrao",
        "academia": "Rigan Mchado"
      },
      {
        "posicao": 3,
        "nome": "Joseph Chrristopher",
        "academia": "NTMMA"
      },
      {
        "posicao": 3,
        "nome": "Curtis Hill",
        "academia": "Gracie Humaita"
      }
    ]
  },
  {
    "categoria": "Master 1 / Brown / Male / Medium Heavy",
    "ranking": [
      {
        "posicao": 1,
        "nome": "Wilson Sgai",
        "academia": "Ryan Gracie"
      },
      {
        "posicao": 2,
        "nome": "Jeff Messina",
        "academia": "BJJ Revolution Team"
      },
      {
        "posicao": 3,
        "nome": "Jeston Pages",
        "academia": "Genesis JJ"
      }
    ]
  },
  {
    "categoria": "Master 1 / Brown / Male / Heavy",
    "ranking": [
      {
        "posicao": 1,
        "nome": "Brian Caldwell",
        "academia": "Brazilian Top Team"
      },
      {
        "posicao": 2,
        "nome": "Michael Aref",
        "academia": "Megaton"
      },
      {
        "posicao": 3,
        "nome": "Danny Dlask",
        "academia": "Gracie Barra"
      },
      {
        "posicao": 3,
        "nome": "David Heck",
        "academia": "Brasa"
      }
    ]
  },
  {
    "categoria": "Master 1 / Brown / Male / Super Heavy",
    "ranking": [
      {
        "posicao": 1,
        "nome": "Cliff Fonseca",
        "academia": "Guardians"
      },
      {
        "posicao": 2,
        "nome": "Humberto Borges",
        "academia": "Alliance"
      },
      {
        "posicao": 3,
        "nome": "Tyler Bosard",
        "academia": "Cantu JJ"
      },
      {
        "posicao": 3,
        "nome": "Ray Casias",
        "academia": "Lloyd Irvin"
      }
    ]
  },
  {
    "categoria": "Master 1 / Brown / Male / Ultra Heavy",
    "ranking": [
      {
        "posicao": 1,
        "nome": "Justin Jacobs",
        "academia": "Saulo Ribeiro"
      },
      {
        "posicao": 2,
        "nome": "Brandon Ruiz",
        "academia": "Machado JJ"
      },
      {
        "posicao": 3,
        "nome": "Francelino Oliveira",
        "academia": "Nova Uniao"
      },
      {
        "posicao": 3,
        "nome": "Mike Rogers",
        "academia": "Vaghi Martial Arts"
      }
    ]
  },
  {
    "categoria": "Master 1 / Brown / Male / Open Class",
    "ranking": [
      {
        "posicao": 1,
        "nome": "Mike Rogers",
        "academia": "Vaghi Martial Arts"
      },
      {
        "posicao": 2,
        "nome": "Gunter Scarboza",
        "academia": "Competition"
      },
      {
        "posicao": 3,
        "nome": "Francelino Oliveira",
        "academia": "Nova Uniao"
      },
      {
        "posicao": 3,
        "nome": "Alfredo Prado",
        "academia": "Alliance"
      }
    ]
  },
  {
    "categoria": "Master 2 / Brown / Male / Feather",
    "ranking": [
      {
        "posicao": 1,
        "nome": "Jimmy Salamanca",
        "academia": "Megaton"
      }
    ]
  },
  {
    "categoria": "Master 2 / Brown / Male / Light",
    "ranking": [
      {
        "posicao": 1,
        "nome": "Adrian Ricci",
        "academia": "Minesota Martial Arts"
      },
      {
        "posicao": 2,
        "nome": "Gil Olivas",
        "academia": "Claudio Franca"
      },
      {
        "posicao": 3,
        "nome": "Chris Vigil",
        "academia": "Pittman's Academy"
      },
      {
        "posicao": 3,
        "nome": "Francois Deniau",
        "academia": "Gracie Humaita"
      }
    ]
  },
  {
    "categoria": "Master 2 / Brown / Male / Middle",
    "ranking": [
      {
        "posicao": 1,
        "nome": "Brian Burke",
        "academia": "Alliance"
      },
      {
        "posicao": 2,
        "nome": "Edward Kennedy",
        "academia": "Alliance"
      },
      {
        "posicao": 3,
        "nome": "Mike Crowford",
        "academia": "Yamasaki Academy"
      },
      {
        "posicao": 3,
        "nome": "Keebo Robinson",
        "academia": "Sergio Penha JJ"
      }
    ]
  },
  {
    "categoria": "Master 2 / Brown / Male / Medium Heavy",
    "ranking": [
      {
        "posicao": 1,
        "nome": "Jeff Malasek",
        "academia": "Alliance"
      },
      {
        "posicao": 2,
        "nome": "Brandon Hetzler",
        "academia": "Rickson"
      },
      {
        "posicao": 3,
        "nome": "Rexie Barnum",
        "academia": "Gracie Barra"
      },
      {
        "posicao": 3,
        "nome": "Chris Hammell",
        "academia": "USA Bjj"
      }
    ]
  },
  {
    "categoria": "Master 2 / Brown / Male / Heavy",
    "ranking": [
      {
        "posicao": 1,
        "nome": "Josh Noblin",
        "academia": "Alliance"
      },
      {
        "posicao": 2,
        "nome": "Jeff Meszaros",
        "academia": "Gracie Barra Vancouver"
      },
      {
        "posicao": 3,
        "nome": "Corby Poulis",
        "academia": "USA Bjj"
      }
    ]
  },
  {
    "categoria": "Master 2 / Brown / Male / Super Heavy",
    "ranking": [
      {
        "posicao": 1,
        "nome": "Anders Thelin",
        "academia": "Vasteras Bjj Team"
      }
    ]
  },
  {
    "categoria": "Master 2 / Brown / Male / Ultra Heavy",
    "ranking": [
      {
        "posicao": 1,
        "nome": "Bill Walters",
        "academia": "Balance"
      },
      {
        "posicao": 2,
        "nome": "Gerald Harris",
        "academia": "Rigan Mchado"
      },
      {
        "posicao": 3,
        "nome": "Rick Gaffey",
        "academia": "Gracie Barra"
      },
      {
        "posicao": 3,
        "nome": "Rudy Jimenez",
        "academia": "Carlson Gracie Team"
      }
    ]
  },
  {
    "categoria": "Master 2 / Brown / Male / Open Class",
    "ranking": [
      {
        "posicao": 1,
        "nome": "Chris Hammell",
        "academia": "USA Bjj"
      },
      {
        "posicao": 2,
        "nome": "Mario Deveault",
        "academia": "Shuswap BJJ"
      },
      {
        "posicao": 3,
        "nome": "Max Masuzawa",
        "academia": "Max Academy"
      },
      {
        "posicao": 3,
        "nome": "Jeff Meszaros",
        "academia": "Gracie Barra Vancouver"
      }
    ]
  },
  {
    "categoria": "Master 3 / Brown / Male / Middle",
    "ranking": [
      {
        "posicao": 1,
        "nome": "Jordan Blanchard",
        "academia": "Gracie Barra"
      },
      {
        "posicao": 2,
        "nome": "Geraldo Azevedo",
        "academia": "Alliance"
      },
      {
        "posicao": 3,
        "nome": "Don Whitefield",
        "academia": "De La Riva"
      },
      {
        "posicao": 3,
        "nome": "Jim De Stefano",
        "academia": "Gracie Humaita"
      }
    ]
  },
  {
    "categoria": "Master 3 / Brown / Male / Medium Heavy",
    "ranking": [
      {
        "posicao": 1,
        "nome": "Gary Matsch",
        "academia": "Nova Uniao Arizona"
      },
      {
        "posicao": 2,
        "nome": "Billy Fletcher",
        "academia": "Alliance"
      },
      {
        "posicao": 3,
        "nome": "Tony Cole",
        "academia": "Cassio Werneck"
      },
      {
        "posicao": 3,
        "nome": "Nathaniel Lane",
        "academia": "Clube de JJ Pitbull"
      }
    ]
  },
  {
    "categoria": "Master 3 / Brown / Male / Super Heavy",
    "ranking": [
      {
        "posicao": 1,
        "nome": "Jose Donizetti",
        "academia": "Xtreme Gold Team"
      },
      {
        "posicao": 2,
        "nome": "Paolo Pacana",
        "academia": "Gracie Barra"
      }
    ]
  },
  {
    "categoria": "Master 3 / Brown / Male / Ultra Heavy",
    "ranking": [
      {
        "posicao": 1,
        "nome": "John Kennedy",
        "academia": "BJJ Revolution Team"
      },
      {
        "posicao": 2,
        "nome": "Raymond Huxen",
        "academia": "Saulo Ribeiro"
      },
      {
        "posicao": 3,
        "nome": "Michael Vann",
        "academia": "Claudio Franca"
      },
      {
        "posicao": 3,
        "nome": "Gary Monroe",
        "academia": "Gracie Barra"
      }
    ]
  },
  {
    "categoria": "Master 4 / Brown / Male / Feather",
    "ranking": [
      {
        "posicao": 1,
        "nome": "Steven Young",
        "academia": "Gracie Barra"
      },
      {
        "posicao": 2,
        "nome": "Mark Van Schuyver",
        "academia": "Alliance"
      },
      {
        "posicao": 3,
        "nome": "Don Charley",
        "academia": "Team Mica"
      }
    ]
  },
  {
    "categoria": "Master 4 / Brown / Male / Light",
    "ranking": [
      {
        "posicao": 1,
        "nome": "Leo Kirby",
        "academia": "Alliance"
      },
      {
        "posicao": 2,
        "nome": "Chris Seals",
        "academia": "Cleber JJ"
      },
      {
        "posicao": 3,
        "nome": "Jeff Thomas",
        "academia": "BJJ Revolution Team"
      },
      {
        "posicao": 3,
        "nome": "Rick Sparks",
        "academia": "Soneca BJJ"
      }
    ]
  },
  {
    "categoria": "Master 4 / Brown / Male / Middle",
    "ranking": [
      {
        "posicao": 1,
        "nome": "Bruce Tafoya",
        "academia": "Gracie Humaita"
      },
      {
        "posicao": 2,
        "nome": "Weija Nyman",
        "academia": "Hilti BJJ"
      },
      {
        "posicao": 3,
        "nome": "Glenn Goodhart",
        "academia": "Alliance"
      },
      {
        "posicao": 3,
        "nome": "Mitch Yount",
        "academia": "Alliance"
      }
    ]
  },
  {
    "categoria": "Master 4 / Brown / Male / Medium Heavy",
    "ranking": [
      {
        "posicao": 1,
        "nome": "Brant Perkins",
        "academia": "Maine JJ"
      },
      {
        "posicao": 2,
        "nome": "Steve Teas",
        "academia": "Carlos Machado"
      }
    ]
  },
  {
    "categoria": "Master 4 / Brown / Male / Heavy",
    "ranking": [
      {
        "posicao": 1,
        "nome": "Philip Myers",
        "academia": "Gracie Barra"
      }
    ]
  },
  {
    "categoria": "Master 4 / Brown / Male / Open Class",
    "ranking": [
      {
        "posicao": 1,
        "nome": "Leo Kirby",
        "academia": "Alliance"
      },
      {
        "posicao": 2,
        "nome": "Steve Teas",
        "academia": "Carlos Machado"
      },
      {
        "posicao": 3,
        "nome": "Bruce Tafoya",
        "academia": "Gracie Humaita"
      },
      {
        "posicao": 3,
        "nome": "Itabura Ferreira",
        "academia": "Pitbull"
      }
    ]
  },
  {
    "categoria": "Adult / Black / Male / Rooster",
    "ranking": [
      {
        "posicao": 1,
        "nome": "Bruno Malfacine",
        "academia": "UGF"
      }
    ]
  },
  {
    "categoria": "Adult / Black / Male / Light Feather",
    "ranking": [
      {
        "posicao": 1,
        "nome": "Carlos Holanda",
        "academia": "Gracie Barra"
      },
      {
        "posicao": 2,
        "nome": "Samuel Braga",
        "academia": "Gracie Barra"
      },
      {
        "posicao": 3,
        "nome": "Leandro Escobar",
        "academia": "Brazilian Top Team"
      },
      {
        "posicao": 3,
        "nome": "Renan Borges",
        "academia": "Brazilian Top Team"
      }
    ]
  },
  {
    "categoria": "Adult / Black / Male / Feather",
    "ranking": [
      {
        "posicao": 1,
        "nome": "Rubens Charles",
        "academia": "Alliance"
      },
      {
        "posicao": 2,
        "nome": "Bruno Frazatto",
        "academia": "Brasa"
      },
      {
        "posicao": 3,
        "nome": "Rodrigo Ranieri",
        "academia": "Brasa"
      },
      {
        "posicao": 3,
        "nome": "Yukinori Sasa",
        "academia": "Paraestra"
      }
    ]
  },
  {
    "categoria": "Adult / Black / Male / Light",
    "ranking": [
      {
        "posicao": 1,
        "nome": "Celso Vinicius",
        "academia": "Ryan Gracie"
      },
      {
        "posicao": 2,
        "nome": "Lucas Lepri",
        "academia": "Alliance"
      },
      {
        "posicao": 3,
        "nome": "Michael Langhi",
        "academia": "Alliance"
      },
      {
        "posicao": 3,
        "nome": "Phillipe de la Monica",
        "academia": "Gracie Barra"
      }
    ]
  },
  {
    "categoria": "Adult / Black / Male / Middle",
    "ranking": [
      {
        "posicao": 1,
        "nome": "Gustavo Campos",
        "academia": "Rickson"
      },
      {
        "posicao": 2,
        "nome": "Otavio Souza",
        "academia": "Gracie Barra"
      },
      {
        "posicao": 3,
        "nome": "Adriano Silva",
        "academia": "Barbosa JJ"
      },
      {
        "posicao": 3,
        "nome": "Lucas Leite",
        "academia": "Brasa"
      }
    ]
  },
  {
    "categoria": "Adult / Black / Male / Medium Heavy",
    "ranking": [
      {
        "posicao": 1,
        "nome": "Andre Galvao",
        "academia": "Brasa"
      },
      {
        "posicao": 2,
        "nome": "Tarsis Humphreys",
        "academia": "Alliance"
      },
      {
        "posicao": 3,
        "nome": "Alexandre de Souza",
        "academia": "Gracie Florianpolis"
      },
      {
        "posicao": 3,
        "nome": "Bruno Fernandes",
        "academia": "Gracie Barra"
      }
    ]
  },
  {
    "categoria": "Adult / Black / Male / Heavy",
    "ranking": [
      {
        "posicao": 1,
        "nome": "Rafael Lovato",
        "academia": "Saulo Ribeiro"
      },
      {
        "posicao": 2,
        "nome": "Roberto Alencar",
        "academia": "Gracie Barra"
      },
      {
        "posicao": 3,
        "nome": "Fernando Di Pierro",
        "academia": "Alliance"
      },
      {
        "posicao": 3,
        "nome": "Roberto Tozi",
        "academia": "Godoi JJ Club"
      }
    ]
  },
  {
    "categoria": "Adult / Black / Male / Super Heavy",
    "ranking": [
      {
        "posicao": 1,
        "nome": "Roberto Abreu",
        "academia": "Nova Geracao"
      },
      {
        "posicao": 2,
        "nome": "Arthur Jacinto",
        "academia": "UGF"
      },
      {
        "posicao": 3,
        "nome": "Ricardo Migliarese",
        "academia": "Balance"
      },
      {
        "posicao": 3,
        "nome": "Marcel Fortuna",
        "academia": "Gracie Florianpolis"
      }
    ]
  },
  {
    "categoria": "Adult / Black / Male / Ultra Heavy",
    "ranking": [
      {
        "posicao": 1,
        "nome": "Luiz Felipe Theodoro",
        "academia": "Godoi JJ Club"
      },
      {
        "posicao": 2,
        "nome": "Bruno Paulista",
        "academia": "Gracie Barra"
      },
      {
        "posicao": 3,
        "nome": "Paulo Ribeiro",
        "academia": "Gracie Barra"
      },
      {
        "posicao": 3,
        "nome": "Vitor Costa",
        "academia": "Brasa"
      }
    ]
  },
  {
    "categoria": "Adult / Black / Male / Open Class",
    "ranking": [
      {
        "posicao": 1,
        "nome": "Andre Galvao",
        "academia": "Brasa"
      },
      {
        "posicao": 2,
        "nome": "Roberto Tozzi",
        "academia": "Godoi JJ Club"
      },
      {
        "posicao": 3,
        "nome": "Luiz Theodoro",
        "academia": "Godoi JJ Club"
      },
      {
        "posicao": 3,
        "nome": "Alexandre Souza",
        "academia": "Gracie Florianpolis"
      }
    ]
  },
  {
    "categoria": "Master 1 / Black / Male / Light Feather",
    "ranking": [
      {
        "posicao": 1,
        "nome": "Makoto Sawada",
        "academia": "Paraestra"
      },
      {
        "posicao": 2,
        "nome": "Rogerio Taborda",
        "academia": "Tatu JJ"
      }
    ]
  },
  {
    "categoria": "Master 1 / Black / Male / Feather",
    "ranking": [
      {
        "posicao": 1,
        "nome": "Mario Correa",
        "academia": "Gracie Barra"
      },
      {
        "posicao": 2,
        "nome": "Danny Alvarez",
        "academia": "Carlos Machado"
      },
      {
        "posicao": 3,
        "nome": "Oliver Reich",
        "academia": "Rey Diogo"
      },
      {
        "posicao": 3,
        "nome": "Gilson dos Santos",
        "academia": "Carlson Gracie Team"
      }
    ]
  },
  {
    "categoria": "Master 1 / Black / Male / Light",
    "ranking": [
      {
        "posicao": 1,
        "nome": "Joao Cunha",
        "academia": "Clube de JJ Pitbull"
      },
      {
        "posicao": 2,
        "nome": "Frederico Sabbatini",
        "academia": "Fight Factory"
      },
      {
        "posicao": 3,
        "nome": "Pedro Viana",
        "academia": "Brazilian Top Team"
      },
      {
        "posicao": 3,
        "nome": "Jared Weiner",
        "academia": "Lloyd Irvin M.A Academy"
      }
    ]
  },
  {
    "categoria": "Master 1 / Black / Male / Middle",
    "ranking": [
      {
        "posicao": 1,
        "nome": "Fabiano Victorino",
        "academia": "X-treme Jiu-Jitsu"
      },
      {
        "posicao": 2,
        "nome": "Luis Fraga",
        "academia": "Ralph Gracie"
      },
      {
        "posicao": 3,
        "nome": "John Carlquist",
        "academia": "Pedro Sauer"
      },
      {
        "posicao": 3,
        "nome": "James Brown",
        "academia": "Star JJ"
      }
    ]
  },
  {
    "categoria": "Master 1 / Black / Male / Medium Heavy",
    "ranking": [
      {
        "posicao": 1,
        "nome": "Cassio Werneck",
        "academia": "Cassio Werneck"
      },
      {
        "posicao": 2,
        "nome": "Paulo Gazze",
        "academia": "Cia Paulista"
      },
      {
        "posicao": 3,
        "nome": "Sergio Silva",
        "academia": "Relson Gracie"
      },
      {
        "posicao": 3,
        "nome": "Mike Weaver",
        "academia": "Claudio Franca"
      }
    ]
  },
  {
    "categoria": "Master 1 / Black / Male / Heavy",
    "ranking": [
      {
        "posicao": 1,
        "nome": "Roberto Godoi",
        "academia": "Godoi JJ Club"
      },
      {
        "posicao": 2,
        "nome": "Robin Gieseler",
        "academia": "Relson Gracie"
      },
      {
        "posicao": 3,
        "nome": "Domicio Lucindo",
        "academia": "Barbosa JJ"
      },
      {
        "posicao": 3,
        "nome": "Walter Vital",
        "academia": "Team Mica"
      }
    ]
  },
  {
    "categoria": "Master 1 / Black / Male / Super Heavy",
    "ranking": [
      {
        "posicao": 1,
        "nome": "Leonardo Dallas Costa",
        "academia": "Leo Dalla"
      },
      {
        "posicao": 2,
        "nome": "Arthur Ruff",
        "academia": "BJJ Revolution Team"
      },
      {
        "posicao": 3,
        "nome": "Jory Malone",
        "academia": "Nova Uniao"
      },
      {
        "posicao": 3,
        "nome": "Jose Eduardo",
        "academia": "Barbosa JJ"
      }
    ]
  },
  {
    "categoria": "Master 1 / Black / Male / Ultra Heavy",
    "ranking": [
      {
        "posicao": 1,
        "nome": "Luigi Mondelli",
        "academia": "American Top Team"
      },
      {
        "posicao": 2,
        "nome": "Adolfo Cezar",
        "academia": "Godoi JJ Club"
      },
      {
        "posicao": 3,
        "nome": "Rodrigo Mendes",
        "academia": "Team Nogueira"
      },
      {
        "posicao": 3,
        "nome": "Rafael Ellwanger",
        "academia": "Gracie Barra"
      }
    ]
  },
  {
    "categoria": "Master 1 / Black / Male / Open Class",
    "ranking": [
      {
        "posicao": 1,
        "nome": "Leonardo Dalla",
        "academia": "Leo Dalla"
      },
      {
        "posicao": 2,
        "nome": "Adolfo Cezae Tozi",
        "academia": "Godoi JJ Club"
      },
      {
        "posicao": 3,
        "nome": "Mike Weaven",
        "academia": "Claudio Franca"
      },
      {
        "posicao": 3,
        "nome": "Walter Vital Jr.",
        "academia": "Team Mica"
      }
    ]
  },
  {
    "categoria": "Master 2 / Black / Male / Light Feather",
    "ranking": [
      {
        "posicao": 1,
        "nome": "Ralph Pires",
        "academia": "Beto e Cia"
      }
    ]
  },
  {
    "categoria": "Master 2 / Black / Male / Feather",
    "ranking": [
      {
        "posicao": 1,
        "nome": "Eduardo Leitao",
        "academia": "Cia Paulista"
      },
      {
        "posicao": 2,
        "nome": "Fernando Lopes",
        "academia": "Godoi JJ Club"
      }
    ]
  },
  {
    "categoria": "Master 2 / Black / Male / Light",
    "ranking": [
      {
        "posicao": 1,
        "nome": "Jack McVicker",
        "academia": "Gracie Humaita"
      },
      {
        "posicao": 2,
        "nome": "Alexandre Freitas",
        "academia": "Gracie Barra"
      },
      {
        "posicao": 3,
        "nome": "Marivan Feitosa",
        "academia": "De La Riva"
      },
      {
        "posicao": 3,
        "nome": "Takashi Ouchi",
        "academia": "Paraestra"
      }
    ]
  },
  {
    "categoria": "Master 2 / Black / Male / Middle",
    "ranking": [
      {
        "posicao": 1,
        "nome": "Marco Nascimento",
        "academia": "Clube de JJ Pitbull"
      },
      {
        "posicao": 2,
        "nome": "Carlos Terrinha",
        "academia": "Gracie Barra"
      },
      {
        "posicao": 3,
        "nome": "Shimizu Sougen",
        "academia": "Paraestra"
      },
      {
        "posicao": 3,
        "nome": "Ricardo Zanelato",
        "academia": "Lotus Club Arizona"
      }
    ]
  },
  {
    "categoria": "Master 2 / Black / Male / Medium Heavy",
    "ranking": [
      {
        "posicao": 1,
        "nome": "Eduardo Rocha",
        "academia": "Saulo Ribeiro"
      },
      {
        "posicao": 2,
        "nome": "Ricardo Miller",
        "academia": "Alliance"
      },
      {
        "posicao": 3,
        "nome": "Peter Lawson",
        "academia": "Renzo Gracie"
      },
      {
        "posicao": 3,
        "nome": "Morgann Paraskevas",
        "academia": "Yamasaki Academy"
      }
    ]
  },
  {
    "categoria": "Master 2 / Black / Male / Heavy",
    "ranking": [
      {
        "posicao": 1,
        "nome": "Amal Easton",
        "academia": "Renzo Gracie"
      },
      {
        "posicao": 2,
        "nome": "Francisco Santana",
        "academia": "Ryan Gracie"
      },
      {
        "posicao": 3,
        "nome": "Yousef Alirezaei",
        "academia": "Star JJ"
      },
      {
        "posicao": 3,
        "nome": "Michael Busby",
        "academia": "Helder Menesse"
      }
    ]
  },
  {
    "categoria": "Master 2 / Black / Male / Super Heavy",
    "ranking": [
      {
        "posicao": 1,
        "nome": "Fabio Gurgel",
        "academia": "Alliance"
      },
      {
        "posicao": 2,
        "nome": "Jason Middaugh",
        "academia": "Fabio Santos"
      },
      {
        "posicao": 3,
        "nome": "Marcio de Lima",
        "academia": "Delima"
      },
      {
        "posicao": 3,
        "nome": "Clahan David",
        "academia": "Ralph Gracie Berkeley"
      }
    ]
  },
  {
    "categoria": "Master 2 / Black / Male / Ultra Heavy",
    "ranking": [
      {
        "posicao": 1,
        "nome": "Luciano Bandeira",
        "academia": "Lotus Club"
      },
      {
        "posicao": 2,
        "nome": "Asa Fuller",
        "academia": "Cleber JJ"
      },
      {
        "posicao": 3,
        "nome": "Jarbas Silva",
        "academia": "Gracie Barra BSB"
      },
      {
        "posicao": 3,
        "nome": "Ronald Assumpcao",
        "academia": "Lotus Club"
      }
    ]
  },
  {
    "categoria": "Master 2 / Black / Male / Open Class",
    "ranking": [
      {
        "posicao": 1,
        "nome": "Fabio Gurgel",
        "academia": "Alliance"
      },
      {
        "posicao": 2,
        "nome": "Carlos Terrinha",
        "academia": "Gracie Barra"
      },
      {
        "posicao": 3,
        "nome": "Francisco Santana",
        "academia": "Ryan Gracie"
      },
      {
        "posicao": 3,
        "nome": "Asa Fuller",
        "academia": "Cleber JJ"
      }
    ]
  },
  {
    "categoria": "Master 3 / Black / Male / Feather",
    "ranking": [
      {
        "posicao": 1,
        "nome": "Richard Travis",
        "academia": "Gracie Barra Culver City"
      },
      {
        "posicao": 2,
        "nome": "Luis Heredia",
        "academia": "Maui Jiu-Jitsu"
      }
    ]
  },
  {
    "categoria": "Master 3 / Black / Male / Light",
    "ranking": [
      {
        "posicao": 1,
        "nome": "Admilson Brites",
        "academia": "Gracie Humaita"
      },
      {
        "posicao": 2,
        "nome": "Vince Vanderlipe",
        "academia": "Claudio Franca"
      },
      {
        "posicao": 3,
        "nome": "Pete Loncarevich",
        "academia": "Lotus Club"
      },
      {
        "posicao": 3,
        "nome": "Marcelo Gheler",
        "academia": "Competition"
      }
    ]
  },
  {
    "categoria": "Master 3 / Black / Male / Middle",
    "ranking": [
      {
        "posicao": 1,
        "nome": "Jason Culbreth",
        "academia": "Team Roc"
      }
    ]
  },
  {
    "categoria": "Master 3 / Black / Male / Medium Heavy",
    "ranking": [
      {
        "posicao": 1,
        "nome": "Ben Guerriero",
        "academia": "American Top Team"
      },
      {
        "posicao": 2,
        "nome": "Amilcar Cipili",
        "academia": "Team Mica"
      },
      {
        "posicao": 3,
        "nome": "Evaldo Lima",
        "academia": "Neutral Grounds"
      }
    ]
  },
  {
    "categoria": "Master 3 / Black / Male / Heavy",
    "ranking": [
      {
        "posicao": 1,
        "nome": "Ailson Brites",
        "academia": "Jucao"
      },
      {
        "posicao": 2,
        "nome": "Ed Beneville",
        "academia": "Joe Moreira"
      },
      {
        "posicao": 3,
        "nome": "Alvis Solis",
        "academia": "Solis Martial Arts"
      },
      {
        "posicao": 3,
        "nome": "Chris Chard",
        "academia": "Jungle Fight Team"
      }
    ]
  },
  {
    "categoria": "Master 3 / Black / Male / Super Heavy",
    "ranking": [
      {
        "posicao": 1,
        "nome": "Adilson Lima",
        "academia": "Gracie Barra"
      },
      {
        "posicao": 2,
        "nome": "Oswaldo Godoi",
        "academia": "Godoi JJ Club"
      },
      {
        "posicao": 3,
        "nome": "Adrien Domimgues",
        "academia": "Godoi JJ Club"
      }
    ]
  },
  {
    "categoria": "Master 3 / Black / Male / Ultra Heavy",
    "ranking": [
      {
        "posicao": 1,
        "nome": "Ricardo Pires",
        "academia": "Legion BJJ"
      },
      {
        "posicao": 2,
        "nome": "Luis Filho",
        "academia": "Luis Filho Team"
      }
    ]
  },
  {
    "categoria": "Master 3 / Black / Male / Open Class",
    "ranking": [
      {
        "posicao": 1,
        "nome": "Ailson Brites",
        "academia": "Jucao"
      },
      {
        "posicao": 2,
        "nome": "Admilson Brites",
        "academia": "Gracie Humaita"
      },
      {
        "posicao": 3,
        "nome": "Adrien Domingues",
        "academia": "Godoi JJ Club"
      },
      {
        "posicao": 3,
        "nome": "Osvaldo Godoi",
        "academia": "Godoi JJ Club"
      }
    ]
  },
  {
    "categoria": "Master 4 / Black / Male / Light",
    "ranking": [
      {
        "posicao": 1,
        "nome": "Chewy Ybarra",
        "academia": "Cleber JJ"
      },
      {
        "posicao": 2,
        "nome": "Jon Bjorksten",
        "academia": "Alliance"
      },
      {
        "posicao": 3,
        "nome": "Fabio Santos",
        "academia": "Fabio Santos"
      }
    ]
  },
  {
    "categoria": "Master 4 / Black / Male / Middle",
    "ranking": [
      {
        "posicao": 1,
        "nome": "Richard Young",
        "academia": "Gracie Barra"
      }
    ]
  },
  {
    "categoria": "Master 4 / Black / Male / Medium Heavy",
    "ranking": [
      {
        "posicao": 1,
        "nome": "Daniel Thomas",
        "academia": "Claudio Franca"
      },
      {
        "posicao": 2,
        "nome": "Milton Del Carlo",
        "academia": "Cia Paulista"
      }
    ]
  },
  {
    "categoria": "Master 4 / Black / Male / Heavy",
    "ranking": [
      {
        "posicao": 1,
        "nome": "Aldo Filho",
        "academia": "Aloisio Silva"
      }
    ]
  },
  {
    "categoria": "Master 4 / Black / Male / Super Heavy",
    "ranking": [
      {
        "posicao": 1,
        "nome": "James Boran",
        "academia": "Boran JJ"
      },
      {
        "posicao": 2,
        "nome": "casey Olsen",
        "academia": "RCJ Machado"
      }
    ]
  },
  {
    "categoria": "Master 4 / Black / Male / Ultra Heavy",
    "ranking": [
      {
        "posicao": 1,
        "nome": "Pat Hardy",
        "academia": "Team Lutter"
      }
    ]
  },
  {
    "categoria": "Master 4 / Black / Male / Open Class",
    "ranking": [
      {
        "posicao": 1,
        "nome": "James Boran",
        "academia": "Boran JJ"
      },
      {
        "posicao": 2,
        "nome": "Richard Young",
        "academia": "Gracie Barra"
      },
      {
        "posicao": 3,
        "nome": "Aldo Filho",
        "academia": "Aloisio Silva"
      }
    ]
  },
  {
    "categoria": "Adult / Brown Black / Female / Light Feather",
    "ranking": [
      {
        "posicao": 1,
        "nome": "Michelle Nicolini",
        "academia": "Brasa"
      }
    ]
  },
  {
    "categoria": "Adult / Brown Black / Female / Light",
    "ranking": [
      {
        "posicao": 1,
        "nome": "Gisele Braga",
        "academia": "BJJ Revolution Team"
      }
    ]
  },
  {
    "categoria": "Adult / Brown Black / Female / Middle",
    "ranking": [
      {
        "posicao": 1,
        "nome": "Ana Laura Cordeiro",
        "academia": "Gracie Barra"
      },
      {
        "posicao": 2,
        "nome": "Hanete Staack",
        "academia": "Carlson Gracie Team"
      },
      {
        "posicao": 3,
        "nome": "Emily Kwok",
        "academia": "Ricardo Almeida JJ"
      }
    ]
  },
  {
    "categoria": "Adult / Brown Black / Female / Medium Heavy",
    "ranking": [
      {
        "posicao": 1,
        "nome": "Luciana Dias",
        "academia": "Gracie Humaita"
      },
      {
        "posicao": 2,
        "nome": "Christina Thomas",
        "academia": "Relson Gracie"
      },
      {
        "posicao": 3,
        "nome": "Gabrielle Garcia",
        "academia": "Triumph"
      },
      {
        "posicao": 3,
        "nome": "Maria do Carmo Teixeira",
        "academia": "Carmen Cascagrossa"
      }
    ]
  },
  {
    "categoria": "Adult / Brown Black / Female / Open Class",
    "ranking": [
      {
        "posicao": 1,
        "nome": "Luciana Dias",
        "academia": "Gracie Humaita"
      },
      {
        "posicao": 2,
        "nome": "Michelle Nicolini",
        "academia": "Brasa"
      },
      {
        "posicao": 3,
        "nome": "Gabrielle Garcia",
        "academia": "Triumph"
      },
      {
        "posicao": 3,
        "nome": "Christina Thomas",
        "academia": "Relson Gracie"
      }
    ]
  },
  {
    "rankingAcademias": {
      "Adult Male": [
        {
          "posicao": 1,
          "academia": "Alliance",
          "pontos": 0
        },
        {
          "posicao": 2,
          "academia": "Gracie Barra",
          "pontos": 0
        },
        {
          "posicao": 3,
          "academia": "Brasa",
          "pontos": 0
        }
      ],
      "Adult Female": [
        {
          "posicao": 1,
          "academia": "Gracie Humaita",
          "pontos": 0
        },
        {
          "posicao": 2,
          "academia": "Gracie Barra",
          "pontos": 0
        },
        {
          "posicao": 3,
          "academia": "Alliance",
          "pontos": 0
        }
      ],
      "Masters": [
        {
          "posicao": 1,
          "academia": "Alliance",
          "pontos": 0
        },
        {
          "posicao": 2,
          "academia": "Saulo Ribeiro",
          "pontos": 0
        },
        {
          "posicao": 3,
          "academia": "BJJ Revolution Team",
          "pontos": 0
        }
      ],
      "Juvenile": [
        {
          "posicao": 1,
          "academia": "Team Mica",
          "pontos": 0
        },
        {
          "posicao": 2,
          "academia": "Alliance",
          "pontos": 0
        },
        {
          "posicao": 3,
          "academia": "Open Door",
          "pontos": 0
        }
      ],
      "Novice": [
        {
          "posicao": 1,
          "academia": "Rickson Gracie",
          "pontos": 0
        },
        {
          "posicao": 2,
          "academia": "Open Door",
          "pontos": 0
        },
        {
          "posicao": 3,
          "academia": "BJJ Revolution Team",
          "pontos": 0
        }
      ]
    }
  }
]